<?xml version="1.0" encoding="utf-8"?>
<ArrayOfModeloPadre xmlns:xsi="http://www.w3.org/2001/XMLSchema-instance" xmlns:xsd="http://www.w3.org/2001/XMLSchema">
  <ModeloPadre>
    <ListOrganos>
      <ModeloOrgano>
        <ModeloOrganoId>Humano</ModeloOrganoId>
        <pos>
          <x>0.667718768</x>
          <y>1.11</y>
          <z>-0.8108183</z>
        </pos>
        <rot>
          <x>0</x>
          <y>1</y>
          <z>0</z>
          <w>-1.47422281E-06</w>
          <eulerAngles>
            <x>0</x>
            <y>180.000183</y>
            <z>0</z>
          </eulerAngles>
        </rot>
      </ModeloOrgano>
      <ModeloOrgano>
        <ModeloOrganoId>SistemaNervioso</ModeloOrganoId>
        <pos>
          <x>0.6561434</x>
          <y>-0.000410676</y>
          <z>-1.95548224</z>
        </pos>
        <rot>
          <x>-1.042433E-06</x>
          <y>-0.7071068</y>
          <z>-0.7071068</z>
          <w>1.042433E-06</w>
          <eulerAngles>
            <x>270</x>
            <y>180.000183</y>
            <z>0</z>
          </eulerAngles>
        </rot>
      </ModeloOrgano>
      <ModeloOrgano>
        <ModeloOrganoId>Nervous_Nerves_Left_Geo</ModeloOrganoId>
        <pos>
          <x>0.656143546</x>
          <y>-14.2898521</y>
          <z>-1.48515081</z>
        </pos>
        <rot>
          <x>-1.042433E-06</x>
          <y>-0.7071068</y>
          <z>-0.7071068</z>
          <w>1.042433E-06</w>
          <eulerAngles>
            <x>270</x>
            <y>180.000183</y>
            <z>0</z>
          </eulerAngles>
        </rot>
      </ModeloOrgano>
      <ModeloOrgano>
        <ModeloOrganoId>Nervous_Nerves_Left_Geo_MeshPart0</ModeloOrganoId>
        <pos>
          <x>0.656143546</x>
          <y>-14.2898521</y>
          <z>-1.48515081</z>
        </pos>
        <rot>
          <x>-1.04243293E-06</x>
          <y>-0.7071068</y>
          <z>-0.7071068</z>
          <w>1.04243293E-06</w>
          <eulerAngles>
            <x>270</x>
            <y>180.000183</y>
            <z>0</z>
          </eulerAngles>
        </rot>
      </ModeloOrgano>
      <ModeloOrgano>
        <ModeloOrganoId>Nervous_Nerves_Left_Geo_MeshPart6</ModeloOrganoId>
        <pos>
          <x>0.656143546</x>
          <y>-14.2898521</y>
          <z>-1.48515081</z>
        </pos>
        <rot>
          <x>-1.04243293E-06</x>
          <y>-0.7071068</y>
          <z>-0.7071068</z>
          <w>1.04243293E-06</w>
          <eulerAngles>
            <x>270</x>
            <y>180.000183</y>
            <z>0</z>
          </eulerAngles>
        </rot>
      </ModeloOrgano>
      <ModeloOrgano>
        <ModeloOrganoId>Nervous_Nerves_Right_Geo</ModeloOrganoId>
        <pos>
          <x>0.656143546</x>
          <y>-14.2898521</y>
          <z>-1.48515081</z>
        </pos>
        <rot>
          <x>-1.042433E-06</x>
          <y>-0.7071068</y>
          <z>-0.7071068</z>
          <w>1.042433E-06</w>
          <eulerAngles>
            <x>270</x>
            <y>180.000183</y>
            <z>0</z>
          </eulerAngles>
        </rot>
      </ModeloOrgano>
      <ModeloOrgano>
        <ModeloOrganoId>Nervous_Nerves_Right_Geo_MeshPart0</ModeloOrganoId>
        <pos>
          <x>0.656143546</x>
          <y>-14.2898521</y>
          <z>-1.48515081</z>
        </pos>
        <rot>
          <x>-1.04243293E-06</x>
          <y>-0.7071068</y>
          <z>-0.7071068</z>
          <w>1.04243293E-06</w>
          <eulerAngles>
            <x>270</x>
            <y>180.000183</y>
            <z>0</z>
          </eulerAngles>
        </rot>
      </ModeloOrgano>
      <ModeloOrgano>
        <ModeloOrganoId>Nervous_Nerves_Right_Geo_MeshPart1</ModeloOrganoId>
        <pos>
          <x>0.656143546</x>
          <y>-14.2898521</y>
          <z>-1.48515081</z>
        </pos>
        <rot>
          <x>-1.04243293E-06</x>
          <y>-0.7071068</y>
          <z>-0.7071068</z>
          <w>1.04243293E-06</w>
          <eulerAngles>
            <x>270</x>
            <y>180.000183</y>
            <z>0</z>
          </eulerAngles>
        </rot>
      </ModeloOrgano>
      <ModeloOrgano>
        <ModeloOrganoId>Nervous_Nerves_Right_Geo_MeshPart2</ModeloOrganoId>
        <pos>
          <x>0.656143546</x>
          <y>-14.2898521</y>
          <z>-1.48515081</z>
        </pos>
        <rot>
          <x>-1.04243293E-06</x>
          <y>-0.7071068</y>
          <z>-0.7071068</z>
          <w>1.04243293E-06</w>
          <eulerAngles>
            <x>270</x>
            <y>180.000183</y>
            <z>0</z>
          </eulerAngles>
        </rot>
      </ModeloOrgano>
      <ModeloOrgano>
        <ModeloOrganoId>Nervous_Nerves_Right_Geo_MeshPart3</ModeloOrganoId>
        <pos>
          <x>0.656143546</x>
          <y>-14.2898521</y>
          <z>-1.48515081</z>
        </pos>
        <rot>
          <x>-1.04243293E-06</x>
          <y>-0.7071068</y>
          <z>-0.7071068</z>
          <w>1.04243293E-06</w>
          <eulerAngles>
            <x>270</x>
            <y>180.000183</y>
            <z>0</z>
          </eulerAngles>
        </rot>
      </ModeloOrgano>
      <ModeloOrgano>
        <ModeloOrganoId>Nervous_Nerves_Right_Geo_MeshPart4</ModeloOrganoId>
        <pos>
          <x>0.656143546</x>
          <y>-14.2898521</y>
          <z>-1.48515081</z>
        </pos>
        <rot>
          <x>-1.04243293E-06</x>
          <y>-0.7071068</y>
          <z>-0.7071068</z>
          <w>1.04243293E-06</w>
          <eulerAngles>
            <x>270</x>
            <y>180.000183</y>
            <z>0</z>
          </eulerAngles>
        </rot>
      </ModeloOrgano>
      <ModeloOrgano>
        <ModeloOrganoId>Nervous_Nerves_Right_Geo_MeshPart5</ModeloOrganoId>
        <pos>
          <x>0.656143546</x>
          <y>-14.2898521</y>
          <z>-1.48515081</z>
        </pos>
        <rot>
          <x>-1.04243293E-06</x>
          <y>-0.7071068</y>
          <z>-0.7071068</z>
          <w>1.04243293E-06</w>
          <eulerAngles>
            <x>270</x>
            <y>180.000183</y>
            <z>0</z>
          </eulerAngles>
        </rot>
      </ModeloOrgano>
      <ModeloOrgano>
        <ModeloOrganoId>Nervous_Nerves_Right_Geo_MeshPart6</ModeloOrganoId>
        <pos>
          <x>0.656143546</x>
          <y>-14.2898521</y>
          <z>-1.48515081</z>
        </pos>
        <rot>
          <x>-1.04243293E-06</x>
          <y>-0.7071068</y>
          <z>-0.7071068</z>
          <w>1.04243293E-06</w>
          <eulerAngles>
            <x>270</x>
            <y>180.000183</y>
            <z>0</z>
          </eulerAngles>
        </rot>
      </ModeloOrgano>
      <ModeloOrgano>
        <ModeloOrganoId>Nervous_Pituarty_Gland_Geo</ModeloOrganoId>
        <pos>
          <x>0.656143546</x>
          <y>-14.2898521</y>
          <z>-1.48515081</z>
        </pos>
        <rot>
          <x>-1.042433E-06</x>
          <y>-0.7071068</y>
          <z>-0.7071068</z>
          <w>1.042433E-06</w>
          <eulerAngles>
            <x>270</x>
            <y>180.000183</y>
            <z>0</z>
          </eulerAngles>
        </rot>
      </ModeloOrgano>
      <ModeloOrgano>
        <ModeloOrganoId>Nervio_Axilar</ModeloOrganoId>
        <pos>
          <x>-1.9396981</x>
          <y>9.13279</y>
          <z>-1.492073</z>
        </pos>
        <rot>
          <x>0.5911035</x>
          <y>-0.6766222</y>
          <z>-0.32391715</z>
          <w>-0.2964067</w>
          <eulerAngles>
            <x>307.930878</x>
            <y>178.305832</y>
            <z>278.5461</z>
          </eulerAngles>
        </rot>
      </ModeloOrgano>
      <ModeloOrgano>
        <ModeloOrganoId>Nervio_Axilar</ModeloOrganoId>
        <pos>
          <x>-2.1768837</x>
          <y>9.162041</y>
          <z>-1.42053545</z>
        </pos>
        <rot>
          <x>0.528694332</x>
          <y>-0.711700737</y>
          <z>-0.4378928</z>
          <w>-0.14904508</w>
          <eulerAngles>
            <x>308.657349</x>
            <y>203.679031</y>
            <z>275.278259</z>
          </eulerAngles>
        </rot>
      </ModeloOrgano>
      <ModeloOrgano>
        <ModeloOrganoId>Nervio_Axilar</ModeloOrganoId>
        <pos>
          <x>-2.405007</x>
          <y>9.169989</y>
          <z>-1.25743055</z>
        </pos>
        <rot>
          <x>0.5225178</x>
          <y>-0.7171869</y>
          <z>-0.461051852</z>
          <w>-0.007029817</w>
          <eulerAngles>
            <x>318.035736</x>
            <y>219.377136</y>
            <z>272.220734</z>
          </eulerAngles>
        </rot>
      </ModeloOrgano>
      <ModeloOrgano>
        <ModeloOrganoId>Nervio_Axilar</ModeloOrganoId>
        <pos>
          <x>-2.64632463</x>
          <y>9.195901</y>
          <z>-1.09432554</z>
        </pos>
        <rot>
          <x>0.519632</x>
          <y>-0.741701543</y>
          <z>-0.412157238</z>
          <w>-0.09993994</w>
          <eulerAngles>
            <x>314.335541</x>
            <y>203.626968</y>
            <z>279.9053</z>
          </eulerAngles>
        </rot>
      </ModeloOrgano>
      <ModeloOrgano>
        <ModeloOrganoId>Nervio_Axilar</ModeloOrganoId>
        <pos>
          <x>-2.82405424</x>
          <y>9.239936</y>
          <z>-0.942189753</z>
        </pos>
        <rot>
          <x>0.42226088</x>
          <y>-0.770174861</y>
          <z>-0.4566954</z>
          <w>0.141265929</w>
          <eulerAngles>
            <x>324.255737</x>
            <y>228.013458</y>
            <z>286.1862</z>
          </eulerAngles>
        </rot>
      </ModeloOrgano>
      <ModeloOrgano>
        <ModeloOrganoId>Nervio_Axilar</ModeloOrganoId>
        <pos>
          <x>-2.87556028</x>
          <y>9.255515</y>
          <z>-0.8094489</z>
        </pos>
        <rot>
          <x>0.4195118</x>
          <y>-0.655371845</y>
          <z>-0.589130044</z>
          <w>0.217769682</w>
          <eulerAngles>
            <x>323.8796</x>
            <y>254.857834</y>
            <z>266.726349</z>
          </eulerAngles>
        </rot>
      </ModeloOrgano>
      <ModeloOrgano>
        <ModeloOrganoId>Nervio_Axilar</ModeloOrganoId>
        <pos>
          <x>-2.96776342</x>
          <y>9.196537</y>
          <z>-0.691174269</z>
        </pos>
        <rot>
          <x>0.6234878</x>
          <y>-0.570451</y>
          <z>-0.5346096</z>
          <w>0.006433062</w>
          <eulerAngles>
            <x>322.992828</x>
            <y>237.564941</y>
            <z>244.077988</z>
          </eulerAngles>
        </rot>
      </ModeloOrgano>
      <ModeloOrgano>
        <ModeloOrganoId>Nervio_Axilar</ModeloOrganoId>
        <pos>
          <x>-3.11195</x>
          <y>9.159179</y>
          <z>-0.6008782</z>
        </pos>
        <rot>
          <x>0.6173382</x>
          <y>-0.65055716</y>
          <z>-0.439391226</z>
          <w>-0.0510335043</w>
          <eulerAngles>
            <x>320.601685</x>
            <y>218.033127</y>
            <z>258.932465</z>
          </eulerAngles>
        </rot>
      </ModeloOrgano>
      <ModeloOrgano>
        <ModeloOrganoId>Nervio_Axilar</ModeloOrganoId>
        <pos>
          <x>-3.32528925</x>
          <y>9.13787651</y>
          <z>-0.484033972</z>
        </pos>
        <rot>
          <x>0.604245543</x>
          <y>-0.6809832</y>
          <z>-0.3996442</z>
          <w>-0.106929958</w>
          <eulerAngles>
            <x>317.660248</x>
            <y>207.153061</y>
            <z>266.148041</z>
          </eulerAngles>
        </rot>
      </ModeloOrgano>
      <ModeloOrgano>
        <ModeloOrganoId>Nervio_Axilar</ModeloOrganoId>
        <pos>
          <x>-4.095664</x>
          <y>9.006248</y>
          <z>-0.397233516</z>
        </pos>
        <rot>
          <x>0.738767564</x>
          <y>-0.5636897</y>
          <z>-0.284925461</z>
          <w>-0.2351469</w>
          <eulerAngles>
            <x>318.03653</x>
            <y>192.1017</y>
            <z>250.032516</z>
          </eulerAngles>
        </rot>
      </ModeloOrgano>
      <ModeloOrgano>
        <ModeloOrganoId>Nervio_Axilar</ModeloOrganoId>
        <pos>
          <x>-3.60603285</x>
          <y>9.107354</y>
          <z>-0.41138342</z>
        </pos>
        <rot>
          <x>0.602368236</x>
          <y>-0.5591794</y>
          <z>-0.4601644</z>
          <w>-0.335737675</w>
          <eulerAngles>
            <x>293.204529</x>
            <y>207.003723</y>
            <z>247.749344</z>
          </eulerAngles>
        </rot>
      </ModeloOrgano>
      <ModeloOrgano>
        <ModeloOrganoId>Nervio_Axilar</ModeloOrganoId>
        <pos>
          <x>-3.20622015</x>
          <y>9.153615</y>
          <z>-0.4473119</z>
        </pos>
        <rot>
          <x>0.3494956</x>
          <y>-0.690389633</y>
          <z>-0.611131</z>
          <w>0.166535273</w>
          <eulerAngles>
            <x>313.3286</x>
            <y>253.266144</y>
            <z>270.7301</z>
          </eulerAngles>
        </rot>
      </ModeloOrgano>
      <ModeloOrgano>
        <ModeloOrganoId>Nervio_Axilar</ModeloOrganoId>
        <pos>
          <x>-3.31368351</x>
          <y>9.073814</y>
          <z>-0.2738623</z>
        </pos>
        <rot>
          <x>0.538285553</x>
          <y>-0.4455033</y>
          <z>-0.7115215</z>
          <w>-0.074248</w>
          <eulerAngles>
            <x>314.4466</x>
            <y>271.927368</y>
            <z>212.278778</z>
          </eulerAngles>
        </rot>
      </ModeloOrgano>
      <ModeloOrgano>
        <ModeloOrganoId>Nervio_Axilar</ModeloOrganoId>
        <pos>
          <x>-3.53544855</x>
          <y>8.884636</y>
          <z>-0.166409373</z>
        </pos>
        <rot>
          <x>0.529714942</x>
          <y>-0.342117876</y>
          <z>-0.737344</z>
          <w>-0.2422426</w>
          <eulerAngles>
            <x>310.4338</x>
            <y>288.399536</y>
            <z>180.460953</z>
          </eulerAngles>
        </rot>
      </ModeloOrgano>
      <ModeloOrgano>
        <ModeloOrganoId>Nervio_Axilar</ModeloOrganoId>
        <pos>
          <x>-3.72239876</x>
          <y>8.740291</y>
          <z>-0.118399441</z>
        </pos>
        <rot>
          <x>0.523963153</x>
          <y>-0.2973525</y>
          <z>-0.6997963</z>
          <w>-0.383835077</w>
          <eulerAngles>
            <x>305.074738</x>
            <y>298.4877</y>
            <z>156.883224</z>
          </eulerAngles>
        </rot>
      </ModeloOrgano>
      <ModeloOrgano>
        <ModeloOrganoId>Nervio_Ulnar</ModeloOrganoId>
        <pos>
          <x>-9.333611</x>
          <y>8.248128</y>
          <z>-0.00535208</z>
        </pos>
        <rot>
          <x>0.6460326</x>
          <y>0.6757987</y>
          <z>-0.18661575</z>
          <w>0.30184865</w>
          <eulerAngles>
            <x>39.9588661</x>
            <y>167.4268</y>
            <z>82.8328247</z>
          </eulerAngles>
        </rot>
      </ModeloOrgano>
      <ModeloOrgano>
        <ModeloOrganoId>Nervio_Ulnar</ModeloOrganoId>
        <pos>
          <x>-7.99554729</x>
          <y>8.236352</y>
          <z>0.318783045</z>
        </pos>
        <rot>
          <x>0.7182156</x>
          <y>0.600322</y>
          <z>-0.131890967</z>
          <w>0.3261669</w>
          <eulerAngles>
            <x>38.81959</x>
            <y>164.961472</y>
            <z>94.89315</z>
          </eulerAngles>
        </rot>
      </ModeloOrgano>
      <ModeloOrgano>
        <ModeloOrganoId>Nervio_Ulnar</ModeloOrganoId>
        <pos>
          <x>-6.488022</x>
          <y>8.173877</y>
          <z>0.354388118</z>
        </pos>
        <rot>
          <x>0.705126762</x>
          <y>0.6992462</y>
          <z>-0.113208584</z>
          <w>-0.0321715549</w>
          <eulerAngles>
            <x>6.485472</x>
            <y>191.885864</y>
            <z>91.15566</z>
          </eulerAngles>
        </rot>
      </ModeloOrgano>
      <ModeloOrgano>
        <ModeloOrganoId>Nervio_Ulnar</ModeloOrganoId>
        <pos>
          <x>-5.22737932</x>
          <y>8.199312</y>
          <z>0.09367204</z>
        </pos>
        <rot>
          <x>0.6441134</x>
          <y>0.7579383</y>
          <z>-0.0709991753</z>
          <w>-0.0748778</w>
          <eulerAngles>
            <x>0.639800966</x>
            <y>191.828415</y>
            <z>80.7835846</z>
          </eulerAngles>
        </rot>
      </ModeloOrgano>
      <ModeloOrgano>
        <ModeloOrganoId>Nervio_Ulnar</ModeloOrganoId>
        <pos>
          <x>-4.353038</x>
          <y>8.342388</y>
          <z>-0.140016079</z>
        </pos>
        <rot>
          <x>0.659802258</x>
          <y>0.7397922</y>
          <z>-0.102779083</z>
          <w>-0.08249337</w>
          <eulerAngles>
            <x>2.47661877</x>
            <y>194.94696</y>
            <z>83.78289</z>
          </eulerAngles>
        </rot>
      </ModeloOrgano>
      <ModeloOrgano>
        <ModeloOrganoId>Nervio_Ulnar</ModeloOrganoId>
        <pos>
          <x>-3.51526022</x>
          <y>8.386902</y>
          <z>-0.450011671</z>
        </pos>
        <rot>
          <x>0.6869071</x>
          <y>0.656960964</y>
          <z>0.0395595171</z>
          <w>-0.308214426</w>
          <eulerAngles>
            <x>331.614136</x>
            <y>203.486969</y>
            <z>86.5340042</z>
          </eulerAngles>
        </rot>
      </ModeloOrgano>
      <ModeloOrgano>
        <ModeloOrganoId>Nervio_Ulnar</ModeloOrganoId>
        <pos>
          <x>-2.73073721</x>
          <y>8.443173</y>
          <z>-0.7223333</z>
        </pos>
        <rot>
          <x>0.6401542</x>
          <y>0.7530582</y>
          <z>-0.115454361</z>
          <w>-0.09887645</w>
          <eulerAngles>
            <x>2.710835</x>
            <y>197.281662</y>
            <z>81.14594</z>
          </eulerAngles>
        </rot>
      </ModeloOrgano>
      <ModeloOrgano>
        <ModeloOrganoId>Nervio_Ulnar</ModeloOrganoId>
        <pos>
          <x>0.5747533</x>
          <y>10.5070934</y>
          <z>-0.881313741</z>
        </pos>
        <rot>
          <x>0.549284637</x>
          <y>0.745822668</y>
          <z>-0.3492324</z>
          <w>-0.14167501</w>
          <eulerAngles>
            <x>21.4254951</x>
            <y>219.728821</y>
            <z>80.5621262</z>
          </eulerAngles>
        </rot>
      </ModeloOrgano>
      <ModeloOrgano>
        <ModeloOrganoId>Nervio_Ulnar</ModeloOrganoId>
        <pos>
          <x>0.4143513</x>
          <y>10.4314346</y>
          <z>-0.8806753</z>
        </pos>
        <rot>
          <x>0.526388645</x>
          <y>0.651550353</y>
          <z>-0.194356874</z>
          <w>0.510512352</w>
          <eulerAngles>
            <x>52.2530556</x>
            <y>131.196518</y>
            <z>52.78116</z>
          </eulerAngles>
        </rot>
      </ModeloOrgano>
      <ModeloOrgano>
        <ModeloOrganoId>Nervio_Ulnar</ModeloOrganoId>
        <pos>
          <x>0.151094139</x>
          <y>10.2352543</y>
          <z>-1.06079066</z>
        </pos>
        <rot>
          <x>0.8712408</x>
          <y>-0.24907</y>
          <z>-0.223006859</z>
          <w>-0.359404862</w>
          <eulerAngles>
            <x>312.494263</x>
            <y>198.071838</y>
            <z>203.901917</z>
          </eulerAngles>
        </rot>
      </ModeloOrgano>
      <ModeloOrgano>
        <ModeloOrganoId>Nervio_Ulnar</ModeloOrganoId>
        <pos>
          <x>-0.2005511</x>
          <y>9.912703</y>
          <z>-1.26904178</z>
        </pos>
        <rot>
          <x>0.4627037</x>
          <y>0.8799968</y>
          <z>0.107079335</z>
          <w>-0.006726839</w>
          <eulerAngles>
            <x>348.773743</x>
            <y>174.896515</y>
            <z>55.97284</z>
          </eulerAngles>
        </rot>
      </ModeloOrgano>
      <ModeloOrgano>
        <ModeloOrganoId>Nervio_Ulnar</ModeloOrganoId>
        <pos>
          <x>-0.605928063</x>
          <y>9.72432</y>
          <z>-1.29797339</z>
        </pos>
        <rot>
          <x>0.6015633</x>
          <y>0.79833746</y>
          <z>-0.02784706</z>
          <w>-0.001908617</w>
          <eulerAngles>
            <x>2.416673</x>
            <y>182.096558</y>
            <z>74.04175</z>
          </eulerAngles>
        </rot>
      </ModeloOrgano>
      <ModeloOrgano>
        <ModeloOrganoId>Nervio_Ulnar</ModeloOrganoId>
        <pos>
          <x>-0.943742156</x>
          <y>9.602231</y>
          <z>-1.26013732</z>
        </pos>
        <rot>
          <x>0.551401854</x>
          <y>0.8267035</y>
          <z>-0.0477537848</z>
          <w>-0.101178192</w>
          <eulerAngles>
            <x>358.130524</x>
            <y>192.713089</y>
            <z>67.1974</z>
          </eulerAngles>
        </rot>
      </ModeloOrgano>
      <ModeloOrgano>
        <ModeloOrganoId>Nervio_Ulnar</ModeloOrganoId>
        <pos>
          <x>-1.27933049</x>
          <y>9.404153</y>
          <z>-1.18319428</z>
        </pos>
        <rot>
          <x>0.453786343</x>
          <y>0.85299027</y>
          <z>-0.009897424</z>
          <w>-0.257658482</w>
          <eulerAngles>
            <x>347.469543</x>
            <y>207.35405</y>
            <z>52.96472</z>
          </eulerAngles>
        </rot>
      </ModeloOrgano>
      <ModeloOrgano>
        <ModeloOrganoId>Nervio_Ulnar</ModeloOrganoId>
        <pos>
          <x>-1.54338133</x>
          <y>9.094318</y>
          <z>-1.07588816</z>
        </pos>
        <rot>
          <x>0.3034842</x>
          <y>0.942245066</y>
          <z>-0.122571543</z>
          <w>-0.0710493848</w>
          <eulerAngles>
            <x>10.8279276</x>
            <y>192.243378</y>
            <z>36.8708153</z>
          </eulerAngles>
        </rot>
      </ModeloOrgano>
      <ModeloOrgano>
        <ModeloOrganoId>Nervio_Ulnar</ModeloOrganoId>
        <pos>
          <x>-1.82237589</x>
          <y>8.815643</y>
          <z>-0.9868541</z>
        </pos>
        <rot>
          <x>0.454257816</x>
          <y>0.877811253</y>
          <z>-0.135605</z>
          <w>0.0686197</w>
          <eulerAngles>
            <x>17.4824276</x>
            <y>180.16394</y>
            <z>54.747364</z>
          </eulerAngles>
        </rot>
      </ModeloOrgano>
      <ModeloOrgano>
        <ModeloOrganoId>Nervio_Ulnar</ModeloOrganoId>
        <pos>
          <x>-2.14508724</x>
          <y>8.618042</y>
          <z>-0.905310333</z>
        </pos>
        <rot>
          <x>0.528927445</x>
          <y>0.836632133</y>
          <z>-0.126740023</z>
          <w>-0.06495908</w>
          <eulerAngles>
            <x>8.241873</x>
            <y>194.199554</y>
            <z>65.63129</z>
          </eulerAngles>
        </rot>
      </ModeloOrgano>
      <ModeloOrgano>
        <ModeloOrganoId>SistemaOseo</ModeloOrganoId>
        <pos>
          <x>0.658296943</x>
          <y>0</y>
          <z>-1.89992821</z>
        </pos>
        <rot>
          <x>-1.042433E-06</x>
          <y>-0.7071068</y>
          <z>-0.7071068</z>
          <w>1.042433E-06</w>
          <eulerAngles>
            <x>270</x>
            <y>180.000183</y>
            <z>0</z>
          </eulerAngles>
        </rot>
      </ModeloOrgano>
      <ModeloOrgano>
        <ModeloOrganoId>Male_Skeletal_Atlas_Geo</ModeloOrganoId>
        <pos>
          <x>0.659764469</x>
          <y>-14.3173008</y>
          <z>-1.48616147</z>
        </pos>
        <rot>
          <x>-1.042433E-06</x>
          <y>-0.7071068</y>
          <z>-0.7071068</z>
          <w>1.042433E-06</w>
          <eulerAngles>
            <x>270</x>
            <y>180.000183</y>
            <z>0</z>
          </eulerAngles>
        </rot>
      </ModeloOrgano>
      <ModeloOrgano>
        <ModeloOrganoId>Male_Skeletal_Axis_Geo</ModeloOrganoId>
        <pos>
          <x>0.659764469</x>
          <y>-14.3173008</y>
          <z>-1.48616147</z>
        </pos>
        <rot>
          <x>-1.042433E-06</x>
          <y>-0.7071068</y>
          <z>-0.7071068</z>
          <w>1.042433E-06</w>
          <eulerAngles>
            <x>270</x>
            <y>180.000183</y>
            <z>0</z>
          </eulerAngles>
        </rot>
      </ModeloOrgano>
      <ModeloOrgano>
        <ModeloOrganoId>Male_Skeletal_C03_Geo</ModeloOrganoId>
        <pos>
          <x>0.659764469</x>
          <y>-14.3173008</y>
          <z>-1.48616147</z>
        </pos>
        <rot>
          <x>-1.042433E-06</x>
          <y>-0.7071068</y>
          <z>-0.7071068</z>
          <w>1.042433E-06</w>
          <eulerAngles>
            <x>270</x>
            <y>180.000183</y>
            <z>0</z>
          </eulerAngles>
        </rot>
      </ModeloOrgano>
      <ModeloOrgano>
        <ModeloOrganoId>Male_Skeletal_C04_Geo</ModeloOrganoId>
        <pos>
          <x>0.659764469</x>
          <y>-14.3173008</y>
          <z>-1.48616147</z>
        </pos>
        <rot>
          <x>-1.042433E-06</x>
          <y>-0.7071068</y>
          <z>-0.7071068</z>
          <w>1.042433E-06</w>
          <eulerAngles>
            <x>270</x>
            <y>180.000183</y>
            <z>0</z>
          </eulerAngles>
        </rot>
      </ModeloOrgano>
      <ModeloOrgano>
        <ModeloOrganoId>Male_Skeletal_C05_Geo</ModeloOrganoId>
        <pos>
          <x>0.659764469</x>
          <y>-14.3173008</y>
          <z>-1.48616147</z>
        </pos>
        <rot>
          <x>-1.042433E-06</x>
          <y>-0.7071068</y>
          <z>-0.7071068</z>
          <w>1.042433E-06</w>
          <eulerAngles>
            <x>270</x>
            <y>180.000183</y>
            <z>0</z>
          </eulerAngles>
        </rot>
      </ModeloOrgano>
      <ModeloOrgano>
        <ModeloOrganoId>Male_Skeletal_C06_Geo</ModeloOrganoId>
        <pos>
          <x>0.659764469</x>
          <y>-14.3173008</y>
          <z>-1.48616147</z>
        </pos>
        <rot>
          <x>-1.042433E-06</x>
          <y>-0.7071068</y>
          <z>-0.7071068</z>
          <w>1.042433E-06</w>
          <eulerAngles>
            <x>270</x>
            <y>180.000183</y>
            <z>0</z>
          </eulerAngles>
        </rot>
      </ModeloOrgano>
      <ModeloOrgano>
        <ModeloOrganoId>Male_Skeletal_C07_Geo</ModeloOrganoId>
        <pos>
          <x>0.659764469</x>
          <y>-14.3173008</y>
          <z>-1.48616147</z>
        </pos>
        <rot>
          <x>-1.042433E-06</x>
          <y>-0.7071068</y>
          <z>-0.7071068</z>
          <w>1.042433E-06</w>
          <eulerAngles>
            <x>270</x>
            <y>180.000183</y>
            <z>0</z>
          </eulerAngles>
        </rot>
      </ModeloOrgano>
      <ModeloOrgano>
        <ModeloOrganoId>Male_Skeletal_Calcaneus_Right_Foot_Geo</ModeloOrganoId>
        <pos>
          <x>0.659764469</x>
          <y>-14.3173008</y>
          <z>-1.48616147</z>
        </pos>
        <rot>
          <x>-1.042433E-06</x>
          <y>-0.7071068</y>
          <z>-0.7071068</z>
          <w>1.042433E-06</w>
          <eulerAngles>
            <x>270</x>
            <y>180.000183</y>
            <z>0</z>
          </eulerAngles>
        </rot>
      </ModeloOrgano>
      <ModeloOrgano>
        <ModeloOrganoId>Male_Skeletal_Carpals_Right_Hand_Geo</ModeloOrganoId>
        <pos>
          <x>0.659764469</x>
          <y>-14.3173008</y>
          <z>-1.48616147</z>
        </pos>
        <rot>
          <x>-1.042433E-06</x>
          <y>-0.7071068</y>
          <z>-0.7071068</z>
          <w>1.042433E-06</w>
          <eulerAngles>
            <x>270</x>
            <y>180.000183</y>
            <z>0</z>
          </eulerAngles>
        </rot>
      </ModeloOrgano>
      <ModeloOrgano>
        <ModeloOrganoId>Male_Skeletal_Clavical_Geo</ModeloOrganoId>
        <pos>
          <x>0.659764469</x>
          <y>-14.3173008</y>
          <z>-1.48616147</z>
        </pos>
        <rot>
          <x>-1.042433E-06</x>
          <y>-0.7071068</y>
          <z>-0.7071068</z>
          <w>1.042433E-06</w>
          <eulerAngles>
            <x>270</x>
            <y>180.000183</y>
            <z>0</z>
          </eulerAngles>
        </rot>
      </ModeloOrgano>
      <ModeloOrgano>
        <ModeloOrganoId>Male_Skeletal_Costal_Cartilages_Geo</ModeloOrganoId>
        <pos>
          <x>0.659764469</x>
          <y>-14.3173008</y>
          <z>-1.48616147</z>
        </pos>
        <rot>
          <x>-1.042433E-06</x>
          <y>-0.7071068</y>
          <z>-0.7071068</z>
          <w>1.042433E-06</w>
          <eulerAngles>
            <x>270</x>
            <y>180.000183</y>
            <z>0</z>
          </eulerAngles>
        </rot>
      </ModeloOrgano>
      <ModeloOrgano>
        <ModeloOrganoId>Male_Skeletal_Cuboid_Right_Foot_Geo</ModeloOrganoId>
        <pos>
          <x>0.659764469</x>
          <y>-14.3173008</y>
          <z>-1.48616147</z>
        </pos>
        <rot>
          <x>-1.042433E-06</x>
          <y>-0.7071068</y>
          <z>-0.7071068</z>
          <w>1.042433E-06</w>
          <eulerAngles>
            <x>270</x>
            <y>180.000183</y>
            <z>0</z>
          </eulerAngles>
        </rot>
      </ModeloOrgano>
      <ModeloOrgano>
        <ModeloOrganoId>Male_Skeletal_Distal_Phalange_01_Right_Hand_Geo</ModeloOrganoId>
        <pos>
          <x>0.659764469</x>
          <y>-14.3173008</y>
          <z>-1.48616147</z>
        </pos>
        <rot>
          <x>-1.042433E-06</x>
          <y>-0.7071068</y>
          <z>-0.7071068</z>
          <w>1.042433E-06</w>
          <eulerAngles>
            <x>270</x>
            <y>180.000183</y>
            <z>0</z>
          </eulerAngles>
        </rot>
      </ModeloOrgano>
      <ModeloOrgano>
        <ModeloOrganoId>Male_Skeletal_Distal_Phalange_02_Right_Hand_Geo</ModeloOrganoId>
        <pos>
          <x>0.659764469</x>
          <y>-14.3173008</y>
          <z>-1.48616147</z>
        </pos>
        <rot>
          <x>-1.042433E-06</x>
          <y>-0.7071068</y>
          <z>-0.7071068</z>
          <w>1.042433E-06</w>
          <eulerAngles>
            <x>270</x>
            <y>180.000183</y>
            <z>0</z>
          </eulerAngles>
        </rot>
      </ModeloOrgano>
      <ModeloOrgano>
        <ModeloOrganoId>Male_Skeletal_Distal_Phalange_03_Right_Hand_Geo</ModeloOrganoId>
        <pos>
          <x>0.659764469</x>
          <y>-14.3173008</y>
          <z>-1.48616147</z>
        </pos>
        <rot>
          <x>-1.042433E-06</x>
          <y>-0.7071068</y>
          <z>-0.7071068</z>
          <w>1.042433E-06</w>
          <eulerAngles>
            <x>270</x>
            <y>180.000183</y>
            <z>0</z>
          </eulerAngles>
        </rot>
      </ModeloOrgano>
      <ModeloOrgano>
        <ModeloOrganoId>Male_Skeletal_Distal_Phalange_04_Right_Hand_Geo</ModeloOrganoId>
        <pos>
          <x>0.659764469</x>
          <y>-14.3173008</y>
          <z>-1.48616147</z>
        </pos>
        <rot>
          <x>-1.042433E-06</x>
          <y>-0.7071068</y>
          <z>-0.7071068</z>
          <w>1.042433E-06</w>
          <eulerAngles>
            <x>270</x>
            <y>180.000183</y>
            <z>0</z>
          </eulerAngles>
        </rot>
      </ModeloOrgano>
      <ModeloOrgano>
        <ModeloOrganoId>Male_Skeletal_Distal_Phalange_05_Right_Hand_Geo</ModeloOrganoId>
        <pos>
          <x>0.659764469</x>
          <y>-14.3173008</y>
          <z>-1.48616147</z>
        </pos>
        <rot>
          <x>-1.042433E-06</x>
          <y>-0.7071068</y>
          <z>-0.7071068</z>
          <w>1.042433E-06</w>
          <eulerAngles>
            <x>270</x>
            <y>180.000183</y>
            <z>0</z>
          </eulerAngles>
        </rot>
      </ModeloOrgano>
      <ModeloOrgano>
        <ModeloOrganoId>Male_Skeletal_Distal_Phalanges_01_Right_Foot_Geo</ModeloOrganoId>
        <pos>
          <x>0.659764469</x>
          <y>-14.3173008</y>
          <z>-1.48616147</z>
        </pos>
        <rot>
          <x>-1.042433E-06</x>
          <y>-0.7071068</y>
          <z>-0.7071068</z>
          <w>1.042433E-06</w>
          <eulerAngles>
            <x>270</x>
            <y>180.000183</y>
            <z>0</z>
          </eulerAngles>
        </rot>
      </ModeloOrgano>
      <ModeloOrgano>
        <ModeloOrganoId>Male_Skeletal_Distal_Phalanges_02_Right_Foot_Geo</ModeloOrganoId>
        <pos>
          <x>0.659764469</x>
          <y>-14.3173008</y>
          <z>-1.48616147</z>
        </pos>
        <rot>
          <x>-1.042433E-06</x>
          <y>-0.7071068</y>
          <z>-0.7071068</z>
          <w>1.042433E-06</w>
          <eulerAngles>
            <x>270</x>
            <y>180.000183</y>
            <z>0</z>
          </eulerAngles>
        </rot>
      </ModeloOrgano>
      <ModeloOrgano>
        <ModeloOrganoId>Male_Skeletal_Distal_Phalanges_03_Right_Foot_Geo</ModeloOrganoId>
        <pos>
          <x>0.659764469</x>
          <y>-14.3173008</y>
          <z>-1.48616147</z>
        </pos>
        <rot>
          <x>-1.042433E-06</x>
          <y>-0.7071068</y>
          <z>-0.7071068</z>
          <w>1.042433E-06</w>
          <eulerAngles>
            <x>270</x>
            <y>180.000183</y>
            <z>0</z>
          </eulerAngles>
        </rot>
      </ModeloOrgano>
      <ModeloOrgano>
        <ModeloOrganoId>Male_Skeletal_Distal_Phalanges_04_Right_Foot_Geo</ModeloOrganoId>
        <pos>
          <x>0.659764469</x>
          <y>-14.3173008</y>
          <z>-1.48616147</z>
        </pos>
        <rot>
          <x>-1.042433E-06</x>
          <y>-0.7071068</y>
          <z>-0.7071068</z>
          <w>1.042433E-06</w>
          <eulerAngles>
            <x>270</x>
            <y>180.000183</y>
            <z>0</z>
          </eulerAngles>
        </rot>
      </ModeloOrgano>
      <ModeloOrgano>
        <ModeloOrganoId>Male_Skeletal_Distal_Phalanges_05_Right_Foot_Geo</ModeloOrganoId>
        <pos>
          <x>0.659764469</x>
          <y>-14.3173008</y>
          <z>-1.48616147</z>
        </pos>
        <rot>
          <x>-1.042433E-06</x>
          <y>-0.7071068</y>
          <z>-0.7071068</z>
          <w>1.042433E-06</w>
          <eulerAngles>
            <x>270</x>
            <y>180.000183</y>
            <z>0</z>
          </eulerAngles>
        </rot>
      </ModeloOrgano>
      <ModeloOrgano>
        <ModeloOrganoId>Male_Skeletal_Femur_Right_Geo</ModeloOrganoId>
        <pos>
          <x>0.659764469</x>
          <y>-14.3173008</y>
          <z>-1.48616147</z>
        </pos>
        <rot>
          <x>-1.042433E-06</x>
          <y>-0.7071068</y>
          <z>-0.7071068</z>
          <w>1.042433E-06</w>
          <eulerAngles>
            <x>270</x>
            <y>180.000183</y>
            <z>0</z>
          </eulerAngles>
        </rot>
      </ModeloOrgano>
      <ModeloOrgano>
        <ModeloOrganoId>Male_Skeletal_Fibula_Right_Geo</ModeloOrganoId>
        <pos>
          <x>0.659764469</x>
          <y>-14.3173008</y>
          <z>-1.48616147</z>
        </pos>
        <rot>
          <x>-1.042433E-06</x>
          <y>-0.7071068</y>
          <z>-0.7071068</z>
          <w>1.042433E-06</w>
          <eulerAngles>
            <x>270</x>
            <y>180.000183</y>
            <z>0</z>
          </eulerAngles>
        </rot>
      </ModeloOrgano>
      <ModeloOrgano>
        <ModeloOrganoId>Male_Skeletal_Hip_Right_Geo</ModeloOrganoId>
        <pos>
          <x>0.659764469</x>
          <y>-14.3173008</y>
          <z>-1.48616147</z>
        </pos>
        <rot>
          <x>-1.042433E-06</x>
          <y>-0.7071068</y>
          <z>-0.7071068</z>
          <w>1.042433E-06</w>
          <eulerAngles>
            <x>270</x>
            <y>180.000183</y>
            <z>0</z>
          </eulerAngles>
        </rot>
      </ModeloOrgano>
      <ModeloOrgano>
        <ModeloOrganoId>Male_Skeletal_Humerus_Right_Geo</ModeloOrganoId>
        <pos>
          <x>0.659764469</x>
          <y>-14.3173008</y>
          <z>-1.48616147</z>
        </pos>
        <rot>
          <x>-1.042433E-06</x>
          <y>-0.7071068</y>
          <z>-0.7071068</z>
          <w>1.042433E-06</w>
          <eulerAngles>
            <x>270</x>
            <y>180.000183</y>
            <z>0</z>
          </eulerAngles>
        </rot>
      </ModeloOrgano>
      <ModeloOrgano>
        <ModeloOrganoId>Male_Skeletal_Intermediate_Cuneiform_Foot_Geo</ModeloOrganoId>
        <pos>
          <x>0.659764469</x>
          <y>-14.3173008</y>
          <z>-1.48616147</z>
        </pos>
        <rot>
          <x>-1.042433E-06</x>
          <y>-0.7071068</y>
          <z>-0.7071068</z>
          <w>1.042433E-06</w>
          <eulerAngles>
            <x>270</x>
            <y>180.000183</y>
            <z>0</z>
          </eulerAngles>
        </rot>
      </ModeloOrgano>
      <ModeloOrgano>
        <ModeloOrganoId>Male_Skeletal_Intervertabral_Discs_Geo</ModeloOrganoId>
        <pos>
          <x>0.659764469</x>
          <y>-14.3173008</y>
          <z>-1.48616147</z>
        </pos>
        <rot>
          <x>-1.042433E-06</x>
          <y>-0.7071068</y>
          <z>-0.7071068</z>
          <w>1.042433E-06</w>
          <eulerAngles>
            <x>270</x>
            <y>180.000183</y>
            <z>0</z>
          </eulerAngles>
        </rot>
      </ModeloOrgano>
      <ModeloOrgano>
        <ModeloOrganoId>Male_Skeletal_L01_Geo</ModeloOrganoId>
        <pos>
          <x>0.659764469</x>
          <y>-14.3173008</y>
          <z>-1.48616147</z>
        </pos>
        <rot>
          <x>-1.042433E-06</x>
          <y>-0.7071068</y>
          <z>-0.7071068</z>
          <w>1.042433E-06</w>
          <eulerAngles>
            <x>270</x>
            <y>180.000183</y>
            <z>0</z>
          </eulerAngles>
        </rot>
      </ModeloOrgano>
      <ModeloOrgano>
        <ModeloOrganoId>Male_Skeletal_L02_Geo</ModeloOrganoId>
        <pos>
          <x>0.659764469</x>
          <y>-14.3173008</y>
          <z>-1.48616147</z>
        </pos>
        <rot>
          <x>-1.042433E-06</x>
          <y>-0.7071068</y>
          <z>-0.7071068</z>
          <w>1.042433E-06</w>
          <eulerAngles>
            <x>270</x>
            <y>180.000183</y>
            <z>0</z>
          </eulerAngles>
        </rot>
      </ModeloOrgano>
      <ModeloOrgano>
        <ModeloOrganoId>Male_Skeletal_L03_Geo</ModeloOrganoId>
        <pos>
          <x>0.659764469</x>
          <y>-14.3173008</y>
          <z>-1.48616147</z>
        </pos>
        <rot>
          <x>-1.042433E-06</x>
          <y>-0.7071068</y>
          <z>-0.7071068</z>
          <w>1.042433E-06</w>
          <eulerAngles>
            <x>270</x>
            <y>180.000183</y>
            <z>0</z>
          </eulerAngles>
        </rot>
      </ModeloOrgano>
      <ModeloOrgano>
        <ModeloOrganoId>Male_Skeletal_L04_Geo</ModeloOrganoId>
        <pos>
          <x>0.659764469</x>
          <y>-14.3173008</y>
          <z>-1.48616147</z>
        </pos>
        <rot>
          <x>-1.042433E-06</x>
          <y>-0.7071068</y>
          <z>-0.7071068</z>
          <w>1.042433E-06</w>
          <eulerAngles>
            <x>270</x>
            <y>180.000183</y>
            <z>0</z>
          </eulerAngles>
        </rot>
      </ModeloOrgano>
      <ModeloOrgano>
        <ModeloOrganoId>Male_Skeletal_L05_Geo</ModeloOrganoId>
        <pos>
          <x>0.659764469</x>
          <y>-14.3173008</y>
          <z>-1.48616147</z>
        </pos>
        <rot>
          <x>-1.042433E-06</x>
          <y>-0.7071068</y>
          <z>-0.7071068</z>
          <w>1.042433E-06</w>
          <eulerAngles>
            <x>270</x>
            <y>180.000183</y>
            <z>0</z>
          </eulerAngles>
        </rot>
      </ModeloOrgano>
      <ModeloOrgano>
        <ModeloOrganoId>Male_Skeletal_Lateral_Cuneiform_Foot_Geo</ModeloOrganoId>
        <pos>
          <x>0.659764469</x>
          <y>-14.3173008</y>
          <z>-1.48616147</z>
        </pos>
        <rot>
          <x>-1.042433E-06</x>
          <y>-0.7071068</y>
          <z>-0.7071068</z>
          <w>1.042433E-06</w>
          <eulerAngles>
            <x>270</x>
            <y>180.000183</y>
            <z>0</z>
          </eulerAngles>
        </rot>
      </ModeloOrgano>
      <ModeloOrgano>
        <ModeloOrganoId>Male_Skeletal_Lower_Canine_Left_Geo</ModeloOrganoId>
        <pos>
          <x>0.659764469</x>
          <y>-14.3173008</y>
          <z>-1.48616147</z>
        </pos>
        <rot>
          <x>-1.042433E-06</x>
          <y>-0.7071068</y>
          <z>-0.7071068</z>
          <w>1.042433E-06</w>
          <eulerAngles>
            <x>270</x>
            <y>180.000183</y>
            <z>0</z>
          </eulerAngles>
        </rot>
      </ModeloOrgano>
      <ModeloOrgano>
        <ModeloOrganoId>Male_Skeletal_Lower_Canine_Right_Geo</ModeloOrganoId>
        <pos>
          <x>0.659764469</x>
          <y>-14.3173008</y>
          <z>-1.48616147</z>
        </pos>
        <rot>
          <x>-1.042433E-06</x>
          <y>-0.7071068</y>
          <z>-0.7071068</z>
          <w>1.042433E-06</w>
          <eulerAngles>
            <x>270</x>
            <y>180.000183</y>
            <z>0</z>
          </eulerAngles>
        </rot>
      </ModeloOrgano>
      <ModeloOrgano>
        <ModeloOrganoId>Male_Skeletal_Lower_Central_Incisor_Left_Geo</ModeloOrganoId>
        <pos>
          <x>0.659764469</x>
          <y>-14.3173008</y>
          <z>-1.48616147</z>
        </pos>
        <rot>
          <x>-1.042433E-06</x>
          <y>-0.7071068</y>
          <z>-0.7071068</z>
          <w>1.042433E-06</w>
          <eulerAngles>
            <x>270</x>
            <y>180.000183</y>
            <z>0</z>
          </eulerAngles>
        </rot>
      </ModeloOrgano>
      <ModeloOrgano>
        <ModeloOrganoId>Male_Skeletal_Lower_Central_Incisor_Right_Geo</ModeloOrganoId>
        <pos>
          <x>0.659764469</x>
          <y>-14.3173008</y>
          <z>-1.48616147</z>
        </pos>
        <rot>
          <x>-1.042433E-06</x>
          <y>-0.7071068</y>
          <z>-0.7071068</z>
          <w>1.042433E-06</w>
          <eulerAngles>
            <x>270</x>
            <y>180.000183</y>
            <z>0</z>
          </eulerAngles>
        </rot>
      </ModeloOrgano>
      <ModeloOrgano>
        <ModeloOrganoId>Male_Skeletal_Lower_Lateral_Incisor_Left_Geo</ModeloOrganoId>
        <pos>
          <x>0.659764469</x>
          <y>-14.3173008</y>
          <z>-1.48616147</z>
        </pos>
        <rot>
          <x>-1.042433E-06</x>
          <y>-0.7071068</y>
          <z>-0.7071068</z>
          <w>1.042433E-06</w>
          <eulerAngles>
            <x>270</x>
            <y>180.000183</y>
            <z>0</z>
          </eulerAngles>
        </rot>
      </ModeloOrgano>
      <ModeloOrgano>
        <ModeloOrganoId>Male_Skeletal_Lower_Lateral_Incisor_Right_Geo</ModeloOrganoId>
        <pos>
          <x>0.659764469</x>
          <y>-14.3173008</y>
          <z>-1.48616147</z>
        </pos>
        <rot>
          <x>-1.042433E-06</x>
          <y>-0.7071068</y>
          <z>-0.7071068</z>
          <w>1.042433E-06</w>
          <eulerAngles>
            <x>270</x>
            <y>180.000183</y>
            <z>0</z>
          </eulerAngles>
        </rot>
      </ModeloOrgano>
      <ModeloOrgano>
        <ModeloOrganoId>Male_Skeletal_Lower_Molar_1_Left_Geo</ModeloOrganoId>
        <pos>
          <x>0.659764469</x>
          <y>-14.3173008</y>
          <z>-1.48616147</z>
        </pos>
        <rot>
          <x>-1.042433E-06</x>
          <y>-0.7071068</y>
          <z>-0.7071068</z>
          <w>1.042433E-06</w>
          <eulerAngles>
            <x>270</x>
            <y>180.000183</y>
            <z>0</z>
          </eulerAngles>
        </rot>
      </ModeloOrgano>
      <ModeloOrgano>
        <ModeloOrganoId>Male_Skeletal_Lower_Molar_1_Right_Geo</ModeloOrganoId>
        <pos>
          <x>0.659764469</x>
          <y>-14.3173008</y>
          <z>-1.48616147</z>
        </pos>
        <rot>
          <x>-1.042433E-06</x>
          <y>-0.7071068</y>
          <z>-0.7071068</z>
          <w>1.042433E-06</w>
          <eulerAngles>
            <x>270</x>
            <y>180.000183</y>
            <z>0</z>
          </eulerAngles>
        </rot>
      </ModeloOrgano>
      <ModeloOrgano>
        <ModeloOrganoId>Male_Skeletal_Lower_Molar_2_Left_Geo</ModeloOrganoId>
        <pos>
          <x>0.659764469</x>
          <y>-14.3173008</y>
          <z>-1.48616147</z>
        </pos>
        <rot>
          <x>-1.042433E-06</x>
          <y>-0.7071068</y>
          <z>-0.7071068</z>
          <w>1.042433E-06</w>
          <eulerAngles>
            <x>270</x>
            <y>180.000183</y>
            <z>0</z>
          </eulerAngles>
        </rot>
      </ModeloOrgano>
      <ModeloOrgano>
        <ModeloOrganoId>Male_Skeletal_Lower_Molar_2_Right_Geo</ModeloOrganoId>
        <pos>
          <x>0.659764469</x>
          <y>-14.3173008</y>
          <z>-1.48616147</z>
        </pos>
        <rot>
          <x>-1.042433E-06</x>
          <y>-0.7071068</y>
          <z>-0.7071068</z>
          <w>1.042433E-06</w>
          <eulerAngles>
            <x>270</x>
            <y>180.000183</y>
            <z>0</z>
          </eulerAngles>
        </rot>
      </ModeloOrgano>
      <ModeloOrgano>
        <ModeloOrganoId>Male_Skeletal_Lower_Premolar_1_Left_Geo</ModeloOrganoId>
        <pos>
          <x>0.659764469</x>
          <y>-14.3173008</y>
          <z>-1.48616147</z>
        </pos>
        <rot>
          <x>-1.042433E-06</x>
          <y>-0.7071068</y>
          <z>-0.7071068</z>
          <w>1.042433E-06</w>
          <eulerAngles>
            <x>270</x>
            <y>180.000183</y>
            <z>0</z>
          </eulerAngles>
        </rot>
      </ModeloOrgano>
      <ModeloOrgano>
        <ModeloOrganoId>Male_Skeletal_Lower_Premolar_1_Right_Geo</ModeloOrganoId>
        <pos>
          <x>0.659764469</x>
          <y>-14.3173008</y>
          <z>-1.48616147</z>
        </pos>
        <rot>
          <x>-1.042433E-06</x>
          <y>-0.7071068</y>
          <z>-0.7071068</z>
          <w>1.042433E-06</w>
          <eulerAngles>
            <x>270</x>
            <y>180.000183</y>
            <z>0</z>
          </eulerAngles>
        </rot>
      </ModeloOrgano>
      <ModeloOrgano>
        <ModeloOrganoId>Male_Skeletal_Lower_Premolar_2_Left_Geo</ModeloOrganoId>
        <pos>
          <x>0.659764469</x>
          <y>-14.3173008</y>
          <z>-1.48616147</z>
        </pos>
        <rot>
          <x>-1.042433E-06</x>
          <y>-0.7071068</y>
          <z>-0.7071068</z>
          <w>1.042433E-06</w>
          <eulerAngles>
            <x>270</x>
            <y>180.000183</y>
            <z>0</z>
          </eulerAngles>
        </rot>
      </ModeloOrgano>
      <ModeloOrgano>
        <ModeloOrganoId>Male_Skeletal_Lower_Premolar_2_Right_Geo</ModeloOrganoId>
        <pos>
          <x>0.659764469</x>
          <y>-14.3173008</y>
          <z>-1.48616147</z>
        </pos>
        <rot>
          <x>-1.042433E-06</x>
          <y>-0.7071068</y>
          <z>-0.7071068</z>
          <w>1.042433E-06</w>
          <eulerAngles>
            <x>270</x>
            <y>180.000183</y>
            <z>0</z>
          </eulerAngles>
        </rot>
      </ModeloOrgano>
      <ModeloOrgano>
        <ModeloOrganoId>Male_Skeletal_Mandible_Geo</ModeloOrganoId>
        <pos>
          <x>0.659764469</x>
          <y>-14.3173008</y>
          <z>-1.48616147</z>
        </pos>
        <rot>
          <x>-1.042433E-06</x>
          <y>-0.7071068</y>
          <z>-0.7071068</z>
          <w>1.042433E-06</w>
          <eulerAngles>
            <x>270</x>
            <y>180.000183</y>
            <z>0</z>
          </eulerAngles>
        </rot>
      </ModeloOrgano>
      <ModeloOrgano>
        <ModeloOrganoId>Male_Skeletal_Medial_Cuneiform_Foot_Geo</ModeloOrganoId>
        <pos>
          <x>0.659764469</x>
          <y>-14.3173008</y>
          <z>-1.48616147</z>
        </pos>
        <rot>
          <x>-1.042433E-06</x>
          <y>-0.7071068</y>
          <z>-0.7071068</z>
          <w>1.042433E-06</w>
          <eulerAngles>
            <x>270</x>
            <y>180.000183</y>
            <z>0</z>
          </eulerAngles>
        </rot>
      </ModeloOrgano>
      <ModeloOrgano>
        <ModeloOrganoId>Male_Skeletal_Metacarpal_01_Right_Hand_Geo</ModeloOrganoId>
        <pos>
          <x>0.659764469</x>
          <y>-14.3173008</y>
          <z>-1.48616147</z>
        </pos>
        <rot>
          <x>-1.042433E-06</x>
          <y>-0.7071068</y>
          <z>-0.7071068</z>
          <w>1.042433E-06</w>
          <eulerAngles>
            <x>270</x>
            <y>180.000183</y>
            <z>0</z>
          </eulerAngles>
        </rot>
      </ModeloOrgano>
      <ModeloOrgano>
        <ModeloOrganoId>Male_Skeletal_Metacarpal_02_Right_Hand_Geo</ModeloOrganoId>
        <pos>
          <x>0.659764469</x>
          <y>-14.3173008</y>
          <z>-1.48616147</z>
        </pos>
        <rot>
          <x>-1.042433E-06</x>
          <y>-0.7071068</y>
          <z>-0.7071068</z>
          <w>1.042433E-06</w>
          <eulerAngles>
            <x>270</x>
            <y>180.000183</y>
            <z>0</z>
          </eulerAngles>
        </rot>
      </ModeloOrgano>
      <ModeloOrgano>
        <ModeloOrganoId>Male_Skeletal_Metacarpal_03_Right_Hand_Geo</ModeloOrganoId>
        <pos>
          <x>0.659764469</x>
          <y>-14.3173008</y>
          <z>-1.48616147</z>
        </pos>
        <rot>
          <x>-1.042433E-06</x>
          <y>-0.7071068</y>
          <z>-0.7071068</z>
          <w>1.042433E-06</w>
          <eulerAngles>
            <x>270</x>
            <y>180.000183</y>
            <z>0</z>
          </eulerAngles>
        </rot>
      </ModeloOrgano>
      <ModeloOrgano>
        <ModeloOrganoId>Male_Skeletal_Metacarpal_04_Right_Hand_Geo</ModeloOrganoId>
        <pos>
          <x>0.659764469</x>
          <y>-14.3173008</y>
          <z>-1.48616147</z>
        </pos>
        <rot>
          <x>-1.042433E-06</x>
          <y>-0.7071068</y>
          <z>-0.7071068</z>
          <w>1.042433E-06</w>
          <eulerAngles>
            <x>270</x>
            <y>180.000183</y>
            <z>0</z>
          </eulerAngles>
        </rot>
      </ModeloOrgano>
      <ModeloOrgano>
        <ModeloOrganoId>Male_Skeletal_Metacarpal_05_Right_Hand_Geo</ModeloOrganoId>
        <pos>
          <x>0.659764469</x>
          <y>-14.3173008</y>
          <z>-1.48616147</z>
        </pos>
        <rot>
          <x>-1.042433E-06</x>
          <y>-0.7071068</y>
          <z>-0.7071068</z>
          <w>1.042433E-06</w>
          <eulerAngles>
            <x>270</x>
            <y>180.000183</y>
            <z>0</z>
          </eulerAngles>
        </rot>
      </ModeloOrgano>
      <ModeloOrgano>
        <ModeloOrganoId>Male_Skeletal_Metarsal_01_Right_Foot_Geo</ModeloOrganoId>
        <pos>
          <x>0.659764469</x>
          <y>-14.3173008</y>
          <z>-1.48616147</z>
        </pos>
        <rot>
          <x>-1.042433E-06</x>
          <y>-0.7071068</y>
          <z>-0.7071068</z>
          <w>1.042433E-06</w>
          <eulerAngles>
            <x>270</x>
            <y>180.000183</y>
            <z>0</z>
          </eulerAngles>
        </rot>
      </ModeloOrgano>
      <ModeloOrgano>
        <ModeloOrganoId>Male_Skeletal_Metarsal_02_Right_Foot_Geo</ModeloOrganoId>
        <pos>
          <x>0.659764469</x>
          <y>-14.3173008</y>
          <z>-1.48616147</z>
        </pos>
        <rot>
          <x>-1.042433E-06</x>
          <y>-0.7071068</y>
          <z>-0.7071068</z>
          <w>1.042433E-06</w>
          <eulerAngles>
            <x>270</x>
            <y>180.000183</y>
            <z>0</z>
          </eulerAngles>
        </rot>
      </ModeloOrgano>
      <ModeloOrgano>
        <ModeloOrganoId>Male_Skeletal_Metarsal_03_Right_Foot_Geo</ModeloOrganoId>
        <pos>
          <x>0.659764469</x>
          <y>-14.3173008</y>
          <z>-1.48616147</z>
        </pos>
        <rot>
          <x>-1.042433E-06</x>
          <y>-0.7071068</y>
          <z>-0.7071068</z>
          <w>1.042433E-06</w>
          <eulerAngles>
            <x>270</x>
            <y>180.000183</y>
            <z>0</z>
          </eulerAngles>
        </rot>
      </ModeloOrgano>
      <ModeloOrgano>
        <ModeloOrganoId>Male_Skeletal_Metarsal_04_Right_Foot_Geo</ModeloOrganoId>
        <pos>
          <x>0.659764469</x>
          <y>-14.3173008</y>
          <z>-1.48616147</z>
        </pos>
        <rot>
          <x>-1.042433E-06</x>
          <y>-0.7071068</y>
          <z>-0.7071068</z>
          <w>1.042433E-06</w>
          <eulerAngles>
            <x>270</x>
            <y>180.000183</y>
            <z>0</z>
          </eulerAngles>
        </rot>
      </ModeloOrgano>
      <ModeloOrgano>
        <ModeloOrganoId>Male_Skeletal_Metarsal_05_Right_Foot_Geo</ModeloOrganoId>
        <pos>
          <x>0.659764469</x>
          <y>-14.3173008</y>
          <z>-1.48616147</z>
        </pos>
        <rot>
          <x>-1.042433E-06</x>
          <y>-0.7071068</y>
          <z>-0.7071068</z>
          <w>1.042433E-06</w>
          <eulerAngles>
            <x>270</x>
            <y>180.000183</y>
            <z>0</z>
          </eulerAngles>
        </rot>
      </ModeloOrgano>
      <ModeloOrgano>
        <ModeloOrganoId>Male_Skeletal_Middle_Phalange_02_Right_Hand_Geo</ModeloOrganoId>
        <pos>
          <x>0.659764469</x>
          <y>-14.3173008</y>
          <z>-1.48616147</z>
        </pos>
        <rot>
          <x>-1.042433E-06</x>
          <y>-0.7071068</y>
          <z>-0.7071068</z>
          <w>1.042433E-06</w>
          <eulerAngles>
            <x>270</x>
            <y>180.000183</y>
            <z>0</z>
          </eulerAngles>
        </rot>
      </ModeloOrgano>
      <ModeloOrgano>
        <ModeloOrganoId>Male_Skeletal_Middle_Phalange_03_Right_Hand_Geo</ModeloOrganoId>
        <pos>
          <x>0.659764469</x>
          <y>-14.3173008</y>
          <z>-1.48616147</z>
        </pos>
        <rot>
          <x>-1.042433E-06</x>
          <y>-0.7071068</y>
          <z>-0.7071068</z>
          <w>1.042433E-06</w>
          <eulerAngles>
            <x>270</x>
            <y>180.000183</y>
            <z>0</z>
          </eulerAngles>
        </rot>
      </ModeloOrgano>
      <ModeloOrgano>
        <ModeloOrganoId>Male_Skeletal_Middle_Phalange_04_Right_Hand_Geo</ModeloOrganoId>
        <pos>
          <x>0.659764469</x>
          <y>-14.3173008</y>
          <z>-1.48616147</z>
        </pos>
        <rot>
          <x>-1.042433E-06</x>
          <y>-0.7071068</y>
          <z>-0.7071068</z>
          <w>1.042433E-06</w>
          <eulerAngles>
            <x>270</x>
            <y>180.000183</y>
            <z>0</z>
          </eulerAngles>
        </rot>
      </ModeloOrgano>
      <ModeloOrgano>
        <ModeloOrganoId>Male_Skeletal_Middle_Phalange_05_Right_Hand_Geo</ModeloOrganoId>
        <pos>
          <x>0.659764469</x>
          <y>-14.3173008</y>
          <z>-1.48616147</z>
        </pos>
        <rot>
          <x>-1.042433E-06</x>
          <y>-0.7071068</y>
          <z>-0.7071068</z>
          <w>1.042433E-06</w>
          <eulerAngles>
            <x>270</x>
            <y>180.000183</y>
            <z>0</z>
          </eulerAngles>
        </rot>
      </ModeloOrgano>
      <ModeloOrgano>
        <ModeloOrganoId>Male_Skeletal_Middle_Phalanges_02_Right_Foot_Geo</ModeloOrganoId>
        <pos>
          <x>0.659764469</x>
          <y>-14.3173008</y>
          <z>-1.48616147</z>
        </pos>
        <rot>
          <x>-1.042433E-06</x>
          <y>-0.7071068</y>
          <z>-0.7071068</z>
          <w>1.042433E-06</w>
          <eulerAngles>
            <x>270</x>
            <y>180.000183</y>
            <z>0</z>
          </eulerAngles>
        </rot>
      </ModeloOrgano>
      <ModeloOrgano>
        <ModeloOrganoId>Male_Skeletal_Middle_Phalanges_03_Right_Foot_Geo</ModeloOrganoId>
        <pos>
          <x>0.659764469</x>
          <y>-14.3173008</y>
          <z>-1.48616147</z>
        </pos>
        <rot>
          <x>-1.042433E-06</x>
          <y>-0.7071068</y>
          <z>-0.7071068</z>
          <w>1.042433E-06</w>
          <eulerAngles>
            <x>270</x>
            <y>180.000183</y>
            <z>0</z>
          </eulerAngles>
        </rot>
      </ModeloOrgano>
      <ModeloOrgano>
        <ModeloOrganoId>Male_Skeletal_Middle_Phalanges_04_Right_Foot_Geo</ModeloOrganoId>
        <pos>
          <x>0.659764469</x>
          <y>-14.3173008</y>
          <z>-1.48616147</z>
        </pos>
        <rot>
          <x>-1.042433E-06</x>
          <y>-0.7071068</y>
          <z>-0.7071068</z>
          <w>1.042433E-06</w>
          <eulerAngles>
            <x>270</x>
            <y>180.000183</y>
            <z>0</z>
          </eulerAngles>
        </rot>
      </ModeloOrgano>
      <ModeloOrgano>
        <ModeloOrganoId>Male_Skeletal_Middle_Phalanges_05_Right_Foot_Geo</ModeloOrganoId>
        <pos>
          <x>0.659764469</x>
          <y>-14.3173008</y>
          <z>-1.48616147</z>
        </pos>
        <rot>
          <x>-1.042433E-06</x>
          <y>-0.7071068</y>
          <z>-0.7071068</z>
          <w>1.042433E-06</w>
          <eulerAngles>
            <x>270</x>
            <y>180.000183</y>
            <z>0</z>
          </eulerAngles>
        </rot>
      </ModeloOrgano>
      <ModeloOrgano>
        <ModeloOrganoId>Male_Skeletal_Navicular_Right_Foot_Geo</ModeloOrganoId>
        <pos>
          <x>0.659764469</x>
          <y>-14.3173008</y>
          <z>-1.48616147</z>
        </pos>
        <rot>
          <x>-1.042433E-06</x>
          <y>-0.7071068</y>
          <z>-0.7071068</z>
          <w>1.042433E-06</w>
          <eulerAngles>
            <x>270</x>
            <y>180.000183</y>
            <z>0</z>
          </eulerAngles>
        </rot>
      </ModeloOrgano>
      <ModeloOrgano>
        <ModeloOrganoId>Male_Skeletal_Patella_Right_Geo</ModeloOrganoId>
        <pos>
          <x>0.659764469</x>
          <y>-14.3173008</y>
          <z>-1.48616147</z>
        </pos>
        <rot>
          <x>-1.042433E-06</x>
          <y>-0.7071068</y>
          <z>-0.7071068</z>
          <w>1.042433E-06</w>
          <eulerAngles>
            <x>270</x>
            <y>180.000183</y>
            <z>0</z>
          </eulerAngles>
        </rot>
      </ModeloOrgano>
      <ModeloOrgano>
        <ModeloOrganoId>Male_Skeletal_Proximal_Phalange_01_Right_Hand_Geo</ModeloOrganoId>
        <pos>
          <x>0.659764469</x>
          <y>-14.3173008</y>
          <z>-1.48616147</z>
        </pos>
        <rot>
          <x>-1.042433E-06</x>
          <y>-0.7071068</y>
          <z>-0.7071068</z>
          <w>1.042433E-06</w>
          <eulerAngles>
            <x>270</x>
            <y>180.000183</y>
            <z>0</z>
          </eulerAngles>
        </rot>
      </ModeloOrgano>
      <ModeloOrgano>
        <ModeloOrganoId>Male_Skeletal_Proximal_Phalange_02_Right_Hand_Geo</ModeloOrganoId>
        <pos>
          <x>0.659764469</x>
          <y>-14.3173008</y>
          <z>-1.48616147</z>
        </pos>
        <rot>
          <x>-1.042433E-06</x>
          <y>-0.7071068</y>
          <z>-0.7071068</z>
          <w>1.042433E-06</w>
          <eulerAngles>
            <x>270</x>
            <y>180.000183</y>
            <z>0</z>
          </eulerAngles>
        </rot>
      </ModeloOrgano>
      <ModeloOrgano>
        <ModeloOrganoId>Male_Skeletal_Proximal_Phalange_03_Right_Hand_Geo</ModeloOrganoId>
        <pos>
          <x>0.659764469</x>
          <y>-14.3173008</y>
          <z>-1.48616147</z>
        </pos>
        <rot>
          <x>-1.042433E-06</x>
          <y>-0.7071068</y>
          <z>-0.7071068</z>
          <w>1.042433E-06</w>
          <eulerAngles>
            <x>270</x>
            <y>180.000183</y>
            <z>0</z>
          </eulerAngles>
        </rot>
      </ModeloOrgano>
      <ModeloOrgano>
        <ModeloOrganoId>Male_Skeletal_Proximal_Phalange_04_Right_Hand_Geo</ModeloOrganoId>
        <pos>
          <x>0.659764469</x>
          <y>-14.3173008</y>
          <z>-1.48616147</z>
        </pos>
        <rot>
          <x>-1.042433E-06</x>
          <y>-0.7071068</y>
          <z>-0.7071068</z>
          <w>1.042433E-06</w>
          <eulerAngles>
            <x>270</x>
            <y>180.000183</y>
            <z>0</z>
          </eulerAngles>
        </rot>
      </ModeloOrgano>
      <ModeloOrgano>
        <ModeloOrganoId>Male_Skeletal_Proximal_Phalange_05_Right_Hand_Geo</ModeloOrganoId>
        <pos>
          <x>0.659764469</x>
          <y>-14.3173008</y>
          <z>-1.48616147</z>
        </pos>
        <rot>
          <x>-1.042433E-06</x>
          <y>-0.7071068</y>
          <z>-0.7071068</z>
          <w>1.042433E-06</w>
          <eulerAngles>
            <x>270</x>
            <y>180.000183</y>
            <z>0</z>
          </eulerAngles>
        </rot>
      </ModeloOrgano>
      <ModeloOrgano>
        <ModeloOrganoId>Male_Skeletal_Proximal_Phalanges_01_Right_Foot_Geo</ModeloOrganoId>
        <pos>
          <x>0.659764469</x>
          <y>-14.3173008</y>
          <z>-1.48616147</z>
        </pos>
        <rot>
          <x>-1.042433E-06</x>
          <y>-0.7071068</y>
          <z>-0.7071068</z>
          <w>1.042433E-06</w>
          <eulerAngles>
            <x>270</x>
            <y>180.000183</y>
            <z>0</z>
          </eulerAngles>
        </rot>
      </ModeloOrgano>
      <ModeloOrgano>
        <ModeloOrganoId>Male_Skeletal_Proximal_Phalanges_02_Right_Foot_Geo</ModeloOrganoId>
        <pos>
          <x>0.659764469</x>
          <y>-14.3173008</y>
          <z>-1.48616147</z>
        </pos>
        <rot>
          <x>-1.042433E-06</x>
          <y>-0.7071068</y>
          <z>-0.7071068</z>
          <w>1.042433E-06</w>
          <eulerAngles>
            <x>270</x>
            <y>180.000183</y>
            <z>0</z>
          </eulerAngles>
        </rot>
      </ModeloOrgano>
      <ModeloOrgano>
        <ModeloOrganoId>Male_Skeletal_Proximal_Phalanges_03_Right_Foot_Geo</ModeloOrganoId>
        <pos>
          <x>0.659764469</x>
          <y>-14.3173008</y>
          <z>-1.48616147</z>
        </pos>
        <rot>
          <x>-1.042433E-06</x>
          <y>-0.7071068</y>
          <z>-0.7071068</z>
          <w>1.042433E-06</w>
          <eulerAngles>
            <x>270</x>
            <y>180.000183</y>
            <z>0</z>
          </eulerAngles>
        </rot>
      </ModeloOrgano>
      <ModeloOrgano>
        <ModeloOrganoId>Male_Skeletal_Proximal_Phalanges_04_Right_Foot_Geo</ModeloOrganoId>
        <pos>
          <x>0.659764469</x>
          <y>-14.3173008</y>
          <z>-1.48616147</z>
        </pos>
        <rot>
          <x>-1.042433E-06</x>
          <y>-0.7071068</y>
          <z>-0.7071068</z>
          <w>1.042433E-06</w>
          <eulerAngles>
            <x>270</x>
            <y>180.000183</y>
            <z>0</z>
          </eulerAngles>
        </rot>
      </ModeloOrgano>
      <ModeloOrgano>
        <ModeloOrganoId>Male_Skeletal_Proximal_Phalanges_05_Right_Foot_Geo</ModeloOrganoId>
        <pos>
          <x>0.659764469</x>
          <y>-14.3173008</y>
          <z>-1.48616147</z>
        </pos>
        <rot>
          <x>-1.042433E-06</x>
          <y>-0.7071068</y>
          <z>-0.7071068</z>
          <w>1.042433E-06</w>
          <eulerAngles>
            <x>270</x>
            <y>180.000183</y>
            <z>0</z>
          </eulerAngles>
        </rot>
      </ModeloOrgano>
      <ModeloOrgano>
        <ModeloOrganoId>Male_Skeletal_Pubic_Symphysis_Geo</ModeloOrganoId>
        <pos>
          <x>0.659764469</x>
          <y>-14.3173008</y>
          <z>-1.48616147</z>
        </pos>
        <rot>
          <x>-1.042433E-06</x>
          <y>-0.7071068</y>
          <z>-0.7071068</z>
          <w>1.042433E-06</w>
          <eulerAngles>
            <x>270</x>
            <y>180.000183</y>
            <z>0</z>
          </eulerAngles>
        </rot>
      </ModeloOrgano>
      <ModeloOrgano>
        <ModeloOrganoId>Male_Skeletal_Radius_Right_Geo</ModeloOrganoId>
        <pos>
          <x>0.659764469</x>
          <y>-14.3173008</y>
          <z>-1.48616147</z>
        </pos>
        <rot>
          <x>-1.042433E-06</x>
          <y>-0.7071068</y>
          <z>-0.7071068</z>
          <w>1.042433E-06</w>
          <eulerAngles>
            <x>270</x>
            <y>180.000183</y>
            <z>0</z>
          </eulerAngles>
        </rot>
      </ModeloOrgano>
      <ModeloOrgano>
        <ModeloOrganoId>Male_Skeletal_Ribs_01_Geo</ModeloOrganoId>
        <pos>
          <x>0.659764469</x>
          <y>-14.3173008</y>
          <z>-1.48616147</z>
        </pos>
        <rot>
          <x>-1.042433E-06</x>
          <y>-0.7071068</y>
          <z>-0.7071068</z>
          <w>1.042433E-06</w>
          <eulerAngles>
            <x>270</x>
            <y>180.000183</y>
            <z>0</z>
          </eulerAngles>
        </rot>
      </ModeloOrgano>
      <ModeloOrgano>
        <ModeloOrganoId>Male_Skeletal_Ribs_02_Geo</ModeloOrganoId>
        <pos>
          <x>0.659764469</x>
          <y>-14.3173008</y>
          <z>-1.48616147</z>
        </pos>
        <rot>
          <x>-1.042433E-06</x>
          <y>-0.7071068</y>
          <z>-0.7071068</z>
          <w>1.042433E-06</w>
          <eulerAngles>
            <x>270</x>
            <y>180.000183</y>
            <z>0</z>
          </eulerAngles>
        </rot>
      </ModeloOrgano>
      <ModeloOrgano>
        <ModeloOrganoId>Male_Skeletal_Ribs_03_Geo</ModeloOrganoId>
        <pos>
          <x>0.659764469</x>
          <y>-14.3173008</y>
          <z>-1.48616147</z>
        </pos>
        <rot>
          <x>-1.042433E-06</x>
          <y>-0.7071068</y>
          <z>-0.7071068</z>
          <w>1.042433E-06</w>
          <eulerAngles>
            <x>270</x>
            <y>180.000183</y>
            <z>0</z>
          </eulerAngles>
        </rot>
      </ModeloOrgano>
      <ModeloOrgano>
        <ModeloOrganoId>Male_Skeletal_Ribs_04_Geo</ModeloOrganoId>
        <pos>
          <x>0.659764469</x>
          <y>-14.3173008</y>
          <z>-1.48616147</z>
        </pos>
        <rot>
          <x>-1.042433E-06</x>
          <y>-0.7071068</y>
          <z>-0.7071068</z>
          <w>1.042433E-06</w>
          <eulerAngles>
            <x>270</x>
            <y>180.000183</y>
            <z>0</z>
          </eulerAngles>
        </rot>
      </ModeloOrgano>
      <ModeloOrgano>
        <ModeloOrganoId>Male_Skeletal_Ribs_05_Geo</ModeloOrganoId>
        <pos>
          <x>0.659764469</x>
          <y>-14.3173008</y>
          <z>-1.48616147</z>
        </pos>
        <rot>
          <x>-1.042433E-06</x>
          <y>-0.7071068</y>
          <z>-0.7071068</z>
          <w>1.042433E-06</w>
          <eulerAngles>
            <x>270</x>
            <y>180.000183</y>
            <z>0</z>
          </eulerAngles>
        </rot>
      </ModeloOrgano>
      <ModeloOrgano>
        <ModeloOrganoId>Male_Skeletal_Ribs_06_Geo</ModeloOrganoId>
        <pos>
          <x>0.659764469</x>
          <y>-14.3173008</y>
          <z>-1.48616147</z>
        </pos>
        <rot>
          <x>-1.042433E-06</x>
          <y>-0.7071068</y>
          <z>-0.7071068</z>
          <w>1.042433E-06</w>
          <eulerAngles>
            <x>270</x>
            <y>180.000183</y>
            <z>0</z>
          </eulerAngles>
        </rot>
      </ModeloOrgano>
      <ModeloOrgano>
        <ModeloOrganoId>Male_Skeletal_Ribs_07_Geo</ModeloOrganoId>
        <pos>
          <x>0.659764469</x>
          <y>-14.3173008</y>
          <z>-1.48616147</z>
        </pos>
        <rot>
          <x>-1.042433E-06</x>
          <y>-0.7071068</y>
          <z>-0.7071068</z>
          <w>1.042433E-06</w>
          <eulerAngles>
            <x>270</x>
            <y>180.000183</y>
            <z>0</z>
          </eulerAngles>
        </rot>
      </ModeloOrgano>
      <ModeloOrgano>
        <ModeloOrganoId>Male_Skeletal_Ribs_08_Geo</ModeloOrganoId>
        <pos>
          <x>0.659764469</x>
          <y>-14.3173008</y>
          <z>-1.48616147</z>
        </pos>
        <rot>
          <x>-1.042433E-06</x>
          <y>-0.7071068</y>
          <z>-0.7071068</z>
          <w>1.042433E-06</w>
          <eulerAngles>
            <x>270</x>
            <y>180.000183</y>
            <z>0</z>
          </eulerAngles>
        </rot>
      </ModeloOrgano>
      <ModeloOrgano>
        <ModeloOrganoId>Male_Skeletal_Ribs_09_Geo</ModeloOrganoId>
        <pos>
          <x>0.659764469</x>
          <y>-14.3173008</y>
          <z>-1.48616147</z>
        </pos>
        <rot>
          <x>-1.042433E-06</x>
          <y>-0.7071068</y>
          <z>-0.7071068</z>
          <w>1.042433E-06</w>
          <eulerAngles>
            <x>270</x>
            <y>180.000183</y>
            <z>0</z>
          </eulerAngles>
        </rot>
      </ModeloOrgano>
      <ModeloOrgano>
        <ModeloOrganoId>Male_Skeletal_Ribs_10_Geo</ModeloOrganoId>
        <pos>
          <x>0.659764469</x>
          <y>-14.3173008</y>
          <z>-1.48616147</z>
        </pos>
        <rot>
          <x>-1.042433E-06</x>
          <y>-0.7071068</y>
          <z>-0.7071068</z>
          <w>1.042433E-06</w>
          <eulerAngles>
            <x>270</x>
            <y>180.000183</y>
            <z>0</z>
          </eulerAngles>
        </rot>
      </ModeloOrgano>
      <ModeloOrgano>
        <ModeloOrganoId>Male_Skeletal_Ribs_11_Geo</ModeloOrganoId>
        <pos>
          <x>0.659764469</x>
          <y>-14.3173008</y>
          <z>-1.48616147</z>
        </pos>
        <rot>
          <x>-1.042433E-06</x>
          <y>-0.7071068</y>
          <z>-0.7071068</z>
          <w>1.042433E-06</w>
          <eulerAngles>
            <x>270</x>
            <y>180.000183</y>
            <z>0</z>
          </eulerAngles>
        </rot>
      </ModeloOrgano>
      <ModeloOrgano>
        <ModeloOrganoId>Male_Skeletal_Ribs_12_Geo</ModeloOrganoId>
        <pos>
          <x>0.659764469</x>
          <y>-14.3173008</y>
          <z>-1.48616147</z>
        </pos>
        <rot>
          <x>-1.042433E-06</x>
          <y>-0.7071068</y>
          <z>-0.7071068</z>
          <w>1.042433E-06</w>
          <eulerAngles>
            <x>270</x>
            <y>180.000183</y>
            <z>0</z>
          </eulerAngles>
        </rot>
      </ModeloOrgano>
      <ModeloOrgano>
        <ModeloOrganoId>Male_Skeletal_Sacrum_Geo</ModeloOrganoId>
        <pos>
          <x>0.659764469</x>
          <y>-14.3173008</y>
          <z>-1.48616147</z>
        </pos>
        <rot>
          <x>-1.042433E-06</x>
          <y>-0.7071068</y>
          <z>-0.7071068</z>
          <w>1.042433E-06</w>
          <eulerAngles>
            <x>270</x>
            <y>180.000183</y>
            <z>0</z>
          </eulerAngles>
        </rot>
      </ModeloOrgano>
      <ModeloOrgano>
        <ModeloOrganoId>Male_Skeletal_Scapula_Right_Geo</ModeloOrganoId>
        <pos>
          <x>0.659764469</x>
          <y>-14.3173008</y>
          <z>-1.48616147</z>
        </pos>
        <rot>
          <x>-1.042433E-06</x>
          <y>-0.7071068</y>
          <z>-0.7071068</z>
          <w>1.042433E-06</w>
          <eulerAngles>
            <x>270</x>
            <y>180.000183</y>
            <z>0</z>
          </eulerAngles>
        </rot>
      </ModeloOrgano>
      <ModeloOrgano>
        <ModeloOrganoId>Male_Skeletal_Skull_Geo</ModeloOrganoId>
        <pos>
          <x>0.659764469</x>
          <y>-14.3173008</y>
          <z>-1.48616147</z>
        </pos>
        <rot>
          <x>-1.042433E-06</x>
          <y>-0.7071068</y>
          <z>-0.7071068</z>
          <w>1.042433E-06</w>
          <eulerAngles>
            <x>270</x>
            <y>180.000183</y>
            <z>0</z>
          </eulerAngles>
        </rot>
      </ModeloOrgano>
      <ModeloOrgano>
        <ModeloOrganoId>Male_Skeletal_Sternum_Geo</ModeloOrganoId>
        <pos>
          <x>0.659764469</x>
          <y>-14.3173008</y>
          <z>-1.48616147</z>
        </pos>
        <rot>
          <x>-1.042433E-06</x>
          <y>-0.7071068</y>
          <z>-0.7071068</z>
          <w>1.042433E-06</w>
          <eulerAngles>
            <x>270</x>
            <y>180.000183</y>
            <z>0</z>
          </eulerAngles>
        </rot>
      </ModeloOrgano>
      <ModeloOrgano>
        <ModeloOrganoId>Male_Skeletal_T01_Geo</ModeloOrganoId>
        <pos>
          <x>0.659764469</x>
          <y>-14.3173008</y>
          <z>-1.48616147</z>
        </pos>
        <rot>
          <x>-1.042433E-06</x>
          <y>-0.7071068</y>
          <z>-0.7071068</z>
          <w>1.042433E-06</w>
          <eulerAngles>
            <x>270</x>
            <y>180.000183</y>
            <z>0</z>
          </eulerAngles>
        </rot>
      </ModeloOrgano>
      <ModeloOrgano>
        <ModeloOrganoId>Male_Skeletal_T02_Geo</ModeloOrganoId>
        <pos>
          <x>0.659764469</x>
          <y>-14.3173008</y>
          <z>-1.48616147</z>
        </pos>
        <rot>
          <x>-1.042433E-06</x>
          <y>-0.7071068</y>
          <z>-0.7071068</z>
          <w>1.042433E-06</w>
          <eulerAngles>
            <x>270</x>
            <y>180.000183</y>
            <z>0</z>
          </eulerAngles>
        </rot>
      </ModeloOrgano>
      <ModeloOrgano>
        <ModeloOrganoId>Male_Skeletal_T03_Geo</ModeloOrganoId>
        <pos>
          <x>0.659764469</x>
          <y>-14.3173008</y>
          <z>-1.48616147</z>
        </pos>
        <rot>
          <x>-1.042433E-06</x>
          <y>-0.7071068</y>
          <z>-0.7071068</z>
          <w>1.042433E-06</w>
          <eulerAngles>
            <x>270</x>
            <y>180.000183</y>
            <z>0</z>
          </eulerAngles>
        </rot>
      </ModeloOrgano>
      <ModeloOrgano>
        <ModeloOrganoId>Male_Skeletal_T04_Geo</ModeloOrganoId>
        <pos>
          <x>0.659764469</x>
          <y>-14.3173008</y>
          <z>-1.48616147</z>
        </pos>
        <rot>
          <x>-1.042433E-06</x>
          <y>-0.7071068</y>
          <z>-0.7071068</z>
          <w>1.042433E-06</w>
          <eulerAngles>
            <x>270</x>
            <y>180.000183</y>
            <z>0</z>
          </eulerAngles>
        </rot>
      </ModeloOrgano>
      <ModeloOrgano>
        <ModeloOrganoId>Male_Skeletal_T05_Geo</ModeloOrganoId>
        <pos>
          <x>0.659764469</x>
          <y>-14.3173008</y>
          <z>-1.48616147</z>
        </pos>
        <rot>
          <x>-1.042433E-06</x>
          <y>-0.7071068</y>
          <z>-0.7071068</z>
          <w>1.042433E-06</w>
          <eulerAngles>
            <x>270</x>
            <y>180.000183</y>
            <z>0</z>
          </eulerAngles>
        </rot>
      </ModeloOrgano>
      <ModeloOrgano>
        <ModeloOrganoId>Male_Skeletal_T06_Geo</ModeloOrganoId>
        <pos>
          <x>0.659764469</x>
          <y>-14.3173008</y>
          <z>-1.48616147</z>
        </pos>
        <rot>
          <x>-1.042433E-06</x>
          <y>-0.7071068</y>
          <z>-0.7071068</z>
          <w>1.042433E-06</w>
          <eulerAngles>
            <x>270</x>
            <y>180.000183</y>
            <z>0</z>
          </eulerAngles>
        </rot>
      </ModeloOrgano>
      <ModeloOrgano>
        <ModeloOrganoId>Male_Skeletal_T07_Geo</ModeloOrganoId>
        <pos>
          <x>0.659764469</x>
          <y>-14.3173008</y>
          <z>-1.48616147</z>
        </pos>
        <rot>
          <x>-1.042433E-06</x>
          <y>-0.7071068</y>
          <z>-0.7071068</z>
          <w>1.042433E-06</w>
          <eulerAngles>
            <x>270</x>
            <y>180.000183</y>
            <z>0</z>
          </eulerAngles>
        </rot>
      </ModeloOrgano>
      <ModeloOrgano>
        <ModeloOrganoId>Male_Skeletal_T08_Geo</ModeloOrganoId>
        <pos>
          <x>0.659764469</x>
          <y>-14.3173008</y>
          <z>-1.48616147</z>
        </pos>
        <rot>
          <x>-1.042433E-06</x>
          <y>-0.7071068</y>
          <z>-0.7071068</z>
          <w>1.042433E-06</w>
          <eulerAngles>
            <x>270</x>
            <y>180.000183</y>
            <z>0</z>
          </eulerAngles>
        </rot>
      </ModeloOrgano>
      <ModeloOrgano>
        <ModeloOrganoId>Male_Skeletal_T09_Geo</ModeloOrganoId>
        <pos>
          <x>0.659764469</x>
          <y>-14.3173008</y>
          <z>-1.48616147</z>
        </pos>
        <rot>
          <x>-1.042433E-06</x>
          <y>-0.7071068</y>
          <z>-0.7071068</z>
          <w>1.042433E-06</w>
          <eulerAngles>
            <x>270</x>
            <y>180.000183</y>
            <z>0</z>
          </eulerAngles>
        </rot>
      </ModeloOrgano>
      <ModeloOrgano>
        <ModeloOrganoId>Male_Skeletal_T10_Geo</ModeloOrganoId>
        <pos>
          <x>0.659764469</x>
          <y>-14.3173008</y>
          <z>-1.48616147</z>
        </pos>
        <rot>
          <x>-1.042433E-06</x>
          <y>-0.7071068</y>
          <z>-0.7071068</z>
          <w>1.042433E-06</w>
          <eulerAngles>
            <x>270</x>
            <y>180.000183</y>
            <z>0</z>
          </eulerAngles>
        </rot>
      </ModeloOrgano>
      <ModeloOrgano>
        <ModeloOrganoId>Male_Skeletal_T11_Geo</ModeloOrganoId>
        <pos>
          <x>0.659764469</x>
          <y>-14.3173008</y>
          <z>-1.48616147</z>
        </pos>
        <rot>
          <x>-1.042433E-06</x>
          <y>-0.7071068</y>
          <z>-0.7071068</z>
          <w>1.042433E-06</w>
          <eulerAngles>
            <x>270</x>
            <y>180.000183</y>
            <z>0</z>
          </eulerAngles>
        </rot>
      </ModeloOrgano>
      <ModeloOrgano>
        <ModeloOrganoId>Male_Skeletal_T12_Geo</ModeloOrganoId>
        <pos>
          <x>0.659764469</x>
          <y>-14.3173008</y>
          <z>-1.48616147</z>
        </pos>
        <rot>
          <x>-1.042433E-06</x>
          <y>-0.7071068</y>
          <z>-0.7071068</z>
          <w>1.042433E-06</w>
          <eulerAngles>
            <x>270</x>
            <y>180.000183</y>
            <z>0</z>
          </eulerAngles>
        </rot>
      </ModeloOrgano>
      <ModeloOrgano>
        <ModeloOrganoId>Male_Skeletal_Talus_Right_Foot_Geo</ModeloOrganoId>
        <pos>
          <x>0.659764469</x>
          <y>-14.3173008</y>
          <z>-1.48616147</z>
        </pos>
        <rot>
          <x>-1.042433E-06</x>
          <y>-0.7071068</y>
          <z>-0.7071068</z>
          <w>1.042433E-06</w>
          <eulerAngles>
            <x>270</x>
            <y>180.000183</y>
            <z>0</z>
          </eulerAngles>
        </rot>
      </ModeloOrgano>
      <ModeloOrgano>
        <ModeloOrganoId>Male_Skeletal_Tibia_Right_Geo</ModeloOrganoId>
        <pos>
          <x>0.659764469</x>
          <y>-14.3173008</y>
          <z>-1.48616147</z>
        </pos>
        <rot>
          <x>-1.042433E-06</x>
          <y>-0.7071068</y>
          <z>-0.7071068</z>
          <w>1.042433E-06</w>
          <eulerAngles>
            <x>270</x>
            <y>180.000183</y>
            <z>0</z>
          </eulerAngles>
        </rot>
      </ModeloOrgano>
      <ModeloOrgano>
        <ModeloOrganoId>Male_Skeletal_Ulna_Right_Geo</ModeloOrganoId>
        <pos>
          <x>0.659764469</x>
          <y>-14.3173008</y>
          <z>-1.48616147</z>
        </pos>
        <rot>
          <x>-1.042433E-06</x>
          <y>-0.7071068</y>
          <z>-0.7071068</z>
          <w>1.042433E-06</w>
          <eulerAngles>
            <x>270</x>
            <y>180.000183</y>
            <z>0</z>
          </eulerAngles>
        </rot>
      </ModeloOrgano>
      <ModeloOrgano>
        <ModeloOrganoId>Male_Skeletal_Upper_Canine_Left_Geo</ModeloOrganoId>
        <pos>
          <x>0.659764469</x>
          <y>-14.3173008</y>
          <z>-1.48616147</z>
        </pos>
        <rot>
          <x>-1.042433E-06</x>
          <y>-0.7071068</y>
          <z>-0.7071068</z>
          <w>1.042433E-06</w>
          <eulerAngles>
            <x>270</x>
            <y>180.000183</y>
            <z>0</z>
          </eulerAngles>
        </rot>
      </ModeloOrgano>
      <ModeloOrgano>
        <ModeloOrganoId>Male_Skeletal_Upper_Canine_Right_Geo</ModeloOrganoId>
        <pos>
          <x>0.659764469</x>
          <y>-14.3173008</y>
          <z>-1.48616147</z>
        </pos>
        <rot>
          <x>-1.042433E-06</x>
          <y>-0.7071068</y>
          <z>-0.7071068</z>
          <w>1.042433E-06</w>
          <eulerAngles>
            <x>270</x>
            <y>180.000183</y>
            <z>0</z>
          </eulerAngles>
        </rot>
      </ModeloOrgano>
      <ModeloOrgano>
        <ModeloOrganoId>Male_Skeletal_Upper_Central_Incisor_Left_Geo</ModeloOrganoId>
        <pos>
          <x>0.659764469</x>
          <y>-14.3173008</y>
          <z>-1.48616147</z>
        </pos>
        <rot>
          <x>-1.042433E-06</x>
          <y>-0.7071068</y>
          <z>-0.7071068</z>
          <w>1.042433E-06</w>
          <eulerAngles>
            <x>270</x>
            <y>180.000183</y>
            <z>0</z>
          </eulerAngles>
        </rot>
      </ModeloOrgano>
      <ModeloOrgano>
        <ModeloOrganoId>Male_Skeletal_Upper_Central_Incisor_Right_Geo</ModeloOrganoId>
        <pos>
          <x>0.659764469</x>
          <y>-14.3173008</y>
          <z>-1.48616147</z>
        </pos>
        <rot>
          <x>-1.042433E-06</x>
          <y>-0.7071068</y>
          <z>-0.7071068</z>
          <w>1.042433E-06</w>
          <eulerAngles>
            <x>270</x>
            <y>180.000183</y>
            <z>0</z>
          </eulerAngles>
        </rot>
      </ModeloOrgano>
      <ModeloOrgano>
        <ModeloOrganoId>Male_Skeletal_Upper_Lateral_Incisor_Left_Geo</ModeloOrganoId>
        <pos>
          <x>0.659764469</x>
          <y>-14.3173008</y>
          <z>-1.48616147</z>
        </pos>
        <rot>
          <x>-1.042433E-06</x>
          <y>-0.7071068</y>
          <z>-0.7071068</z>
          <w>1.042433E-06</w>
          <eulerAngles>
            <x>270</x>
            <y>180.000183</y>
            <z>0</z>
          </eulerAngles>
        </rot>
      </ModeloOrgano>
      <ModeloOrgano>
        <ModeloOrganoId>Male_Skeletal_Upper_Lateral_Incisor_Right_Geo</ModeloOrganoId>
        <pos>
          <x>0.659764469</x>
          <y>-14.3173008</y>
          <z>-1.48616147</z>
        </pos>
        <rot>
          <x>-1.042433E-06</x>
          <y>-0.7071068</y>
          <z>-0.7071068</z>
          <w>1.042433E-06</w>
          <eulerAngles>
            <x>270</x>
            <y>180.000183</y>
            <z>0</z>
          </eulerAngles>
        </rot>
      </ModeloOrgano>
      <ModeloOrgano>
        <ModeloOrganoId>Male_Skeletal_Upper_Molar_1_Left_Geo</ModeloOrganoId>
        <pos>
          <x>0.659764469</x>
          <y>-14.3173008</y>
          <z>-1.48616147</z>
        </pos>
        <rot>
          <x>-1.042433E-06</x>
          <y>-0.7071068</y>
          <z>-0.7071068</z>
          <w>1.042433E-06</w>
          <eulerAngles>
            <x>270</x>
            <y>180.000183</y>
            <z>0</z>
          </eulerAngles>
        </rot>
      </ModeloOrgano>
      <ModeloOrgano>
        <ModeloOrganoId>Male_Skeletal_Upper_Molar_1_Right_Geo</ModeloOrganoId>
        <pos>
          <x>0.659764469</x>
          <y>-14.3173008</y>
          <z>-1.48616147</z>
        </pos>
        <rot>
          <x>-1.042433E-06</x>
          <y>-0.7071068</y>
          <z>-0.7071068</z>
          <w>1.042433E-06</w>
          <eulerAngles>
            <x>270</x>
            <y>180.000183</y>
            <z>0</z>
          </eulerAngles>
        </rot>
      </ModeloOrgano>
      <ModeloOrgano>
        <ModeloOrganoId>Male_Skeletal_Upper_Molar_2_Left_Geo</ModeloOrganoId>
        <pos>
          <x>0.659764469</x>
          <y>-14.3173008</y>
          <z>-1.48616147</z>
        </pos>
        <rot>
          <x>-1.042433E-06</x>
          <y>-0.7071068</y>
          <z>-0.7071068</z>
          <w>1.042433E-06</w>
          <eulerAngles>
            <x>270</x>
            <y>180.000183</y>
            <z>0</z>
          </eulerAngles>
        </rot>
      </ModeloOrgano>
      <ModeloOrgano>
        <ModeloOrganoId>Male_Skeletal_Upper_Molar_2_Right_Geo</ModeloOrganoId>
        <pos>
          <x>0.659764469</x>
          <y>-14.3173008</y>
          <z>-1.48616147</z>
        </pos>
        <rot>
          <x>-1.042433E-06</x>
          <y>-0.7071068</y>
          <z>-0.7071068</z>
          <w>1.042433E-06</w>
          <eulerAngles>
            <x>270</x>
            <y>180.000183</y>
            <z>0</z>
          </eulerAngles>
        </rot>
      </ModeloOrgano>
      <ModeloOrgano>
        <ModeloOrganoId>Male_Skeletal_Upper_Premolar_1_Left_Geo</ModeloOrganoId>
        <pos>
          <x>0.659764469</x>
          <y>-14.3173008</y>
          <z>-1.48616147</z>
        </pos>
        <rot>
          <x>-1.042433E-06</x>
          <y>-0.7071068</y>
          <z>-0.7071068</z>
          <w>1.042433E-06</w>
          <eulerAngles>
            <x>270</x>
            <y>180.000183</y>
            <z>0</z>
          </eulerAngles>
        </rot>
      </ModeloOrgano>
      <ModeloOrgano>
        <ModeloOrganoId>Male_Skeletal_Upper_Premolar_1_Right_Geo</ModeloOrganoId>
        <pos>
          <x>0.659764469</x>
          <y>-14.3173008</y>
          <z>-1.48616147</z>
        </pos>
        <rot>
          <x>-1.042433E-06</x>
          <y>-0.7071068</y>
          <z>-0.7071068</z>
          <w>1.042433E-06</w>
          <eulerAngles>
            <x>270</x>
            <y>180.000183</y>
            <z>0</z>
          </eulerAngles>
        </rot>
      </ModeloOrgano>
      <ModeloOrgano>
        <ModeloOrganoId>Male_Skeletal_Upper_Premolar_2_Left_Geo</ModeloOrganoId>
        <pos>
          <x>0.659764469</x>
          <y>-14.3173008</y>
          <z>-1.48616147</z>
        </pos>
        <rot>
          <x>-1.042433E-06</x>
          <y>-0.7071068</y>
          <z>-0.7071068</z>
          <w>1.042433E-06</w>
          <eulerAngles>
            <x>270</x>
            <y>180.000183</y>
            <z>0</z>
          </eulerAngles>
        </rot>
      </ModeloOrgano>
      <ModeloOrgano>
        <ModeloOrganoId>Male_Skeletal_Upper_Premolar_2_Right_Geo</ModeloOrganoId>
        <pos>
          <x>0.659764469</x>
          <y>-14.3173008</y>
          <z>-1.48616147</z>
        </pos>
        <rot>
          <x>-1.042433E-06</x>
          <y>-0.7071068</y>
          <z>-0.7071068</z>
          <w>1.042433E-06</w>
          <eulerAngles>
            <x>270</x>
            <y>180.000183</y>
            <z>0</z>
          </eulerAngles>
        </rot>
      </ModeloOrgano>
      <ModeloOrgano>
        <ModeloOrganoId>SistemaMuscular</ModeloOrganoId>
        <pos>
          <x>0.656143</x>
          <y>0.06364703</y>
          <z>-1.72774827</z>
        </pos>
        <rot>
          <x>-1.042433E-06</x>
          <y>-0.7071068</y>
          <z>-0.7071068</z>
          <w>1.042433E-06</w>
          <eulerAngles>
            <x>270</x>
            <y>180.000183</y>
            <z>0</z>
          </eulerAngles>
        </rot>
      </ModeloOrgano>
      <ModeloOrgano>
        <ModeloOrganoId>Biceps_Brachii_Muscle_Right</ModeloOrganoId>
        <pos>
          <x>0.656143248</x>
          <y>-14.3004665</y>
          <z>-1.49262261</z>
        </pos>
        <rot>
          <x>-1.042433E-06</x>
          <y>-0.7071068</y>
          <z>-0.7071068</z>
          <w>1.042433E-06</w>
          <eulerAngles>
            <x>270</x>
            <y>180.000183</y>
            <z>0</z>
          </eulerAngles>
        </rot>
      </ModeloOrgano>
      <ModeloOrgano>
        <ModeloOrganoId>Biceps_Brachii_Right</ModeloOrganoId>
        <pos>
          <x>0.656143248</x>
          <y>-14.3004665</y>
          <z>-1.49262261</z>
        </pos>
        <rot>
          <x>-1.042433E-06</x>
          <y>-0.7071068</y>
          <z>-0.7071068</z>
          <w>1.042433E-06</w>
          <eulerAngles>
            <x>270</x>
            <y>180.000183</y>
            <z>0</z>
          </eulerAngles>
        </rot>
      </ModeloOrgano>
      <ModeloOrgano>
        <ModeloOrganoId>Coracobrachialis_Muscle_Right</ModeloOrganoId>
        <pos>
          <x>0.656143248</x>
          <y>-14.3004665</y>
          <z>-1.49262261</z>
        </pos>
        <rot>
          <x>-1.042433E-06</x>
          <y>-0.7071068</y>
          <z>-0.7071068</z>
          <w>1.042433E-06</w>
          <eulerAngles>
            <x>270</x>
            <y>180.000183</y>
            <z>0</z>
          </eulerAngles>
        </rot>
      </ModeloOrgano>
      <ModeloOrgano>
        <ModeloOrganoId>Deltoideus_Muscle_Right</ModeloOrganoId>
        <pos>
          <x>0.656143248</x>
          <y>-14.3004665</y>
          <z>-1.49262261</z>
        </pos>
        <rot>
          <x>-1.042433E-06</x>
          <y>-0.7071068</y>
          <z>-0.7071068</z>
          <w>1.042433E-06</w>
          <eulerAngles>
            <x>270</x>
            <y>180.000183</y>
            <z>0</z>
          </eulerAngles>
        </rot>
      </ModeloOrgano>
      <ModeloOrgano>
        <ModeloOrganoId>Pronator_Teres_Muscle_Right</ModeloOrganoId>
        <pos>
          <x>0.656143248</x>
          <y>-14.3004665</y>
          <z>-1.49262261</z>
        </pos>
        <rot>
          <x>-1.042433E-06</x>
          <y>-0.7071068</y>
          <z>-0.7071068</z>
          <w>1.042433E-06</w>
          <eulerAngles>
            <x>270</x>
            <y>180.000183</y>
            <z>0</z>
          </eulerAngles>
        </rot>
      </ModeloOrgano>
      <ModeloOrgano>
        <ModeloOrganoId>Tricep_Mucsle_Right</ModeloOrganoId>
        <pos>
          <x>0.656143248</x>
          <y>-14.3004665</y>
          <z>-1.49262261</z>
        </pos>
        <rot>
          <x>-1.042433E-06</x>
          <y>-0.7071068</y>
          <z>-0.7071068</z>
          <w>1.042433E-06</w>
          <eulerAngles>
            <x>270</x>
            <y>180.000183</y>
            <z>0</z>
          </eulerAngles>
        </rot>
      </ModeloOrgano>
      <ModeloOrgano>
        <ModeloOrganoId>Tricep_Muscle_Right</ModeloOrganoId>
        <pos>
          <x>0.656143248</x>
          <y>-14.3004665</y>
          <z>-1.49262261</z>
        </pos>
        <rot>
          <x>-1.042433E-06</x>
          <y>-0.7071068</y>
          <z>-0.7071068</z>
          <w>1.042433E-06</w>
          <eulerAngles>
            <x>270</x>
            <y>180.000183</y>
            <z>0</z>
          </eulerAngles>
        </rot>
      </ModeloOrgano>
      <ModeloOrgano>
        <ModeloOrganoId>Pivot</ModeloOrganoId>
        <pos>
          <x>-5.01</x>
          <y>8.48</y>
          <z>0</z>
        </pos>
        <rot>
          <x>0</x>
          <y>0</y>
          <z>0</z>
          <w>1</w>
          <eulerAngles>
            <x>0</x>
            <y>0</y>
            <z>0</z>
          </eulerAngles>
        </rot>
      </ModeloOrgano>
    </ListOrganos>
    <ModeloPadreId>Humano</ModeloPadreId>
    <pos>
      <x>0.667718768</x>
      <y>1.11</y>
      <z>-0.8108183</z>
    </pos>
    <rot>
      <x>0</x>
      <y>180.000183</y>
      <z>0</z>
    </rot>
    <Camara>
      <CamaraId>0</CamaraId>
      <ZoomCamara>2.68</ZoomCamara>
      <pos>
        <x>-5.01</x>
        <y>8.48</y>
        <z>-40</z>
      </pos>
      <rot>
        <x>0</x>
        <y>0</y>
        <z>0</z>
        <w>1</w>
        <eulerAngles>
          <x>0</x>
          <y>0</y>
          <z>0</z>
        </eulerAngles>
      </rot>
    </Camara>
  </ModeloPadre>
</ArrayOfModeloPadre>